Workbook
Name kythuat: #REF!
Name nhaplieu: #REF!
Name nhaplieuPLHD: #REF!
Name NoidungPLHD: #REF!
Name PLHD: #REF!
Name Thongsothang: #REF!
Name ThongtinHD: #REF!
Name ThongtinPLHD: #REF!

Sheet Contract data
A1: contract date | B1: contract_ID | C1: project_address | D1: province_old | E1: province_new | F1: customer_ID | G1: contract_duration | H1: project_ID | I1: saleman_ID | J1: warranty_period_months | K1: maintenance_period_months | L1: contract_source | M1: elevator_brand | N1: product_ID | O1: shaft_type | P1: elevator_type | Q1: elevator_traction_machine | R1: control_system | S1: contract_value_before_tax | T1: contract_vat_amount | U1: contract_value_after_tax | V1: net_price | W1: discount | X1: customer_commission | Y1: sales_commission | Z1: import_date | AA1: import_staff
A2: 45500 | B2: 1001/HĐ-2024 | C2: thửa 330, tbđ số 1, p. thạnh mỹ lợi, tp. thủ đức, tp. hcm | D2: TP Hồ Chí Minh | E2: =VLOOKUP(D2,'shipping inf'!B:D,2,FALSE) -> TP Hồ Chí Minh | F2: KH001 | G2: 120 | H2: 2411000101 | I2: D2007 | J2: 24 | K2: 24 | L2: MKT Cơ bản | M2: Sanyo Minh Long | N2: =VLOOKUP(Table1[[#This Row],[elevator_traction_machine]],'Product inf'!A:B,2,FALSE) -> SP015 | O2: Bê tông | P2: Tải khách | Q2: Ziehl-Abegg - Đức | R2: Sanotec DREAM control | S2: 415000000 | U2: 415000000 | V2: 476800000 | Y2: 7000000 | Z2: 45500 | AA2: D200772024
A3: 45306 | B3: 101/HĐ-2024 | C3: căn hộ t21-1 vinhomes grand park, p. long thạnh mỹ, tp. thủ đức, tphcm | D3: TP Hồ Chí Minh | E3: =VLOOKUP(D3,'shipping inf'!B:D,2,FALSE) -> TP Hồ Chí Minh | F3: KH002 | G3: 75 | H3: 2410100101 | I3: D3001 | J3: 24 | K3: 24 | L3: Ban Giám Đốc | M3: Sanyo Minh Long | N3: =VLOOKUP(Table1[[#This Row],[elevator_traction_machine]],'Product inf'!A:B,2,FALSE) -> SP006 | O3: Kết cấu thép | P3: Tải khách | Q3: Sanotec - Nhật Bản | R3: Sanotec DREAM control | S3: 440000000 | U3: 440000000 | Y3: 7557500 | Z3: 45309 | AA3: D300112024
A4: 45671 | B4: 101/HĐ-2025 | C4: thửa 407-408 bình thới, p.14, q.11, tphcm | D4: TP Hồ Chí Minh | E4: =VLOOKUP(D4,'shipping inf'!B:D,2,FALSE) -> TP Hồ Chí Minh | F4: KH003 | G4: 90 | H4: 2510100101 | I4: D3001 | J4: 24 | K4: 12 | L4: Ban Giám Đốc | M4: Sanyo Minh Long | N4: =VLOOKUP(Table1[[#This Row],[elevator_traction_machine]],'Product inf'!A:B,2,FALSE) -> SP006 | O4: Bê tông | P4: Tải khách | Q4: Sanotec - Nhật Bản | R4: Sanotec DREAM control | S4: 372000000 | U4: 372000000 | V4: 367000000 | Y4: 5220000 | Z4: 45671 | AA4: D300112025
A5: 46079 | B5: 101A.ĐL/HĐ-2026 | C5: 366 phan đình phùng, phường xuân hương - đà lạt, lâm đồng | D5: Lâm Đồng | E5: =VLOOKUP(D5,'shipping inf'!B:D,2,FALSE) -> Lâm Đồng | F5: KH004 | G5: 90 | H5: 2610100101 | I5: D3002 | J5: 24 | K5: 24 | L5: Ban Giám Đốc | M5: Sanyo Minh Long | N5: =VLOOKUP(Table1[[#This Row],[elevator_traction_machine]],'Product inf'!A:B,2,FALSE) -> SP006 | O5: Kết cấu thép | P5: Tải khách | Q5: Sanotec - Nhật Bản | R5: Sanotec DREAM control | S5: 400000000 | U5: 400000000 | V5: 400000000 | Z5: 46087 | AA5: D300222026
A6: 45320 | B6: 102/HĐ-2024 | C6: lô p-3, đường số 7, kcn long hậu mở rộng, x. long hậu, h. cần giuộc, long an (fp1) | D6: TP Hồ Chí Minh | E6: =VLOOKUP(D6,'shipping inf'!B:D,2,FALSE) -> TP Hồ Chí Minh | F6: KH005 | G6: 60 | H6: 2410100201 | I6: D3001 | J6: 24 | K6: 12 | L6: Ban Giám Đốc | M6: Sanyo Minh Long | N6: =VLOOKUP(Table1[[#This Row],[elevator_traction_machine]],'Product inf'!A:B,2,FALSE) -> SP006 | O6: Kết cấu thép | P6: Tải khách | Q6: Sanotec - Nhật Bản | R6: Sanotec DREAM control | S6: 1039200000 | T6: 41568000 | U6: 1080768000 | Y6: 12392000 | Z6: 45329 | AA6: D300112024
A7: 45714 | B7: 102/HĐ-2025 | C7: xã trung an, h. củ chi, tphcm | D7: TP Hồ Chí Minh | E7: =VLOOKUP(D7,'shipping inf'!B:D,2,FALSE) -> TP Hồ Chí Minh | F7: KH006 | G7: 150 | H7: 2510100201 | I7: D3001 | J7: 24 | K7: 12 | L7: Ban Giám Đốc | M7: Sanyo Minh Long | N7: =VLOOKUP(Table1[[#This Row],[elevator_traction_machine]],'Product inf'!A:B,2,FALSE) -> SP006 | O7: Bê tông | P7: Tải khách | Q7: Sanotec - Nhật Bản | R7: Sanotec DREAM control | S7: 390000000 | U7: 390000000 | V7: 373000000 | X7: 0 | Y7: 5400000 | Z7: 45726 | AA7: D300122025
A8: 46058 | B8: 102/HĐ-2026 | C8: thửa đất số 06, tbđ 81, p.tân mỹ, tphcm | D8: TP Hồ Chí Minh | E8: =VLOOKUP(D8,'shipping inf'!B:D,2,FALSE) -> TP Hồ Chí Minh | F8: KH007 | G8: 90 | H8: 2610100201 | I8: D3001 | J8: 24 | K8: 24 | L8: Ban Giám Đốc | M8: Sanyo Minh Long | N8: =VLOOKUP(Table1[[#This Row],[elevator_traction_machine]],'Product inf'!A:B,2,FALSE) -> SP006 | O8: Bê tông | P8: Tải khách | Q8: Sanotec - Nhật Bản | R8: Sanotec DREAM control | S8: 557000000 | U8: 557000000 | V8: 556000000 | Z8: 46059 | AA8: D300122026
A9: 45353 | B9: 103/HĐ-2024 | C9: số 12 đường số 10, kp3, p. bình thuận, q.7, tp. hcm | D9: TP Hồ Chí Minh | E9: =VLOOKUP(D9,'shipping inf'!B:D,2,FALSE) -> TP Hồ Chí Minh | F9: KH008 | G9: 70 | H9: 2410100301 | I9: D3001 | J9: 24 | K9: 12 | L9: Ban Giám Đốc | M9: Sanyo Minh Long | N9: =VLOOKUP(Table1[[#This Row],[elevator_traction_machine]],'Product inf'!A:B,2,FALSE) -> SP015 | O9: Bê tông | P9: Tải khách | Q9: Ziehl-Abegg - Đức | R9: Sanotec DREAM control | S9: 454000000 | T9: 20000000 | U9: 474000000 | Y9: 5540000 | Z9: 45360 | AA9: D300132024
A10: 45419 | B10: 104/HĐ-2024 | C10: 314 nguyễn thái sơn, p.4, q. gò vấp, tp. hcm | D10: TP Hồ Chí Minh | E10: =VLOOKUP(D10,'shipping inf'!B:D,2,FALSE) -> TP Hồ Chí Minh | F10: KH009 | G10: 120 | H10: 2410100401 | I10: D3001 | J10: 24 | K10: 12 | L10: Ban Giám Đốc | M10: Sanyo Minh Long | N10: =VLOOKUP(Table1[[#This Row],[elevator_traction_machine]],'Product inf'!A:B,2,FALSE) -> SP015 | O10: Bê tông | P10: Tải khách | Q10: Ziehl-Abegg - Đức | R10: Sanotec DREAM control | S10: 425000000 | U10: 425000000 | X10: 3000000 | Y10: 5250000 | Z10: 45420 | AA10: D300152024
A11: 45721 | B11: 104/HĐ-2025 | C11: 301/16/10 vườn lài, p. an phú đông, q.12, tphcm | D11: TP Hồ Chí Minh | E11: =VLOOKUP(D11,'shipping inf'!B:D,2,FALSE) -> TP Hồ Chí Minh | F11: KH010 | G11: 120 | H11: 2510100401 | I11: D3001 | J11: 24 | K11: 24 | L11: Ban Giám Đốc | M11: Sanyo Minh Long | N11: =VLOOKUP(Table1[[#This Row],[elevator_traction_machine]],'Product inf'!A:B,2,FALSE) -> SP015 | O11: Bê tông | P11: Tải khách | Q11: Ziehl-Abegg - Đức | R11: Sanotec CEN control | S11: 355000000 | U11: 355000000 | V11: 350000000 | X11: 0 | Y11: 5050000 | Z11: 45724 | AA11: D300132025
A12: 46055 | B12: 104/HĐ-2026 | C12: kdc thửa 408, tờ 58/bđđc, p.bình thạnh, tphcm | D12: TP Hồ Chí Minh | E12: =VLOOKUP(D12,'shipping inf'!B:D,2,FALSE) -> TP Hồ Chí Minh | F12: KH011 | G12: 90 | H12: 2610100401 | I12: D3001 | J12: 24 | K12: 24 | L12: Ban Giám Đốc | M12: Sanyo Minh Long | N12: =VLOOKUP(Table1[[#This Row],[elevator_traction_machine]],'Product inf'!A:B,2,FALSE) -> SP006 | O12: Bê tông | P12: Tải khách | Q12: Sanotec - Nhật Bản | R12: Sanotec DREAM control | S12: 800000000 | U12: 800000000 | V12: 800000000 | Z12: 46059 | AA12: D300122026
A13: 46055 | B13: 104/HĐ-2026 | C13: kdc thửa 408, tờ 58/bđđc, p.bình thạnh, tphcm | D13: TP Hồ Chí Minh | E13: =VLOOKUP(D13,'shipping inf'!B:D,2,FALSE) -> TP Hồ Chí Minh | F13: KH011 | G13: 90 | H13: 2610100402 | I13: D3001 | J13: 24 | K13: 24 | L13: Ban Giám Đốc | M13: Sanyo Minh Long | N13: =VLOOKUP(Table1[[#This Row],[elevator_traction_machine]],'Product inf'!A:B,2,FALSE) -> SP006 | O13: Bê tông | P13: Tải khách | Q13: Sanotec - Nhật Bản | R13: Sanotec DREAM control | S13: 800000000 | U13: 800000000 | V13: 800000000 | Z13: 46059 | AA13: D300122026
A14: 45311 | B14: 105/HĐ-2024 | C14: số 60 lê tự tài, p.4, q. phú nhuận, tp. hcm | D14: TP Hồ Chí Minh | E14: =VLOOKUP(D14,'shipping inf'!B:D,2,FALSE) -> TP Hồ Chí Minh | F14: KH011 | G14: 90 | H14: 2410100501 | I14: D3001 | J14: 24 | K14: 12 | L14: Ban Giám Đốc | M14: Sanyo Minh Long | N14: =VLOOKUP(Table1[[#This Row],[elevator_traction_machine]],'Product inf'!A:B,2,FALSE) -> SP006 | O14: Bê tông | P14: Tải khách | Q14: Sanotec - Nhật Bản | R14: Sanotec DREAM control | S14: 380000000 | U14: 380000000 | X14: 3000000 | Y14: 4800000 | Z14: 45311 | AA14: D300112024
A15: 45776 | B15: 105/HĐ-2025 | C15: tòa nhà hội nghị - khối lâu đài lachateau pl1 | D15: TP Hồ Chí Minh | E15: =VLOOKUP(D15,'shipping inf'!B:D,2,FALSE) -> TP Hồ Chí Minh | F15: KH012 | G15: 90 | H15: 2510100502 | I15: D3001 | J15: 24 | K15: 24 | L15: Ban Giám Đốc | M15: Sanyo Minh Long | N15: =VLOOKUP(Table1[[#This Row],[elevator_traction_machine]],'Product inf'!A:B,2,FALSE) -> SP006 | O15: Bê tông | P15: Tải khách | Q15: Sanotec - Nhật Bản | R15: Sanotec DREAM control | S15: 865000000 | T15: 69200000 | U15: 934200000 | V15: 896404000 | Y15: 11050000 | Z15: 45776 | AA15: D300142025
A16: 45776 | B16: 105/HĐ-2025 | C16: tòa nhà hội nghị - khối lâu đài lachateau pl2 | D16: TP Hồ Chí Minh | E16: =VLOOKUP(D16,'shipping inf'!B:D,2,FALSE) -> TP Hồ Chí Minh | F16: KH012 | G16: 90 | H16: 2510100502 | I16: D3001 | J16: 24 | K16: 24 | L16: Ban Giám Đốc | M16: Sanyo Minh Long | N16: =VLOOKUP(Table1[[#This Row],[elevator_traction_machine]],'Product inf'!A:B,2,FALSE) -> SP006 | O16: Bê tông | P16: Tải khách | Q16: Sanotec - Nhật Bản | R16: Sanotec DREAM control | U16: 0 | Z16: 45776 | AA16: D300142025
A17: 46062 | B17: 105/HĐ-2026 | C17: số 29 đường tân canh, p.tân sơn hòa, tphcm | D17: TP Hồ Chí Minh | E17: =VLOOKUP(D17,'shipping inf'!B:D,2,FALSE) -> TP Hồ Chí Minh | F17: KH013 | G17: 90 | H17: 2610100501 | I17: D3001 | J17: 24 | K17: 24 | L17: Ban Giám Đốc | M17: Sanyo Minh Long | N17: =VLOOKUP(Table1[[#This Row],[elevator_traction_machine]],'Product inf'!A:B,2,FALSE) -> SP010 | O17: Kết cấu thép | P17: Tải khách | Q17: Sanotec Eco - Trung Quốc | R17: Sanotec Eco control | S17: 744250000 | U17: 744250000 | V17: 707500000 | Z17: 46062 | AA17: D300122026
A18: 45358 | B18: 106/HĐ-2024 | C18: ấp 3, x. phước kiển, h. nhà bè, tp. hcm (thửa đất số 117, tbđ số 6 ) | D18: TP Hồ Chí Minh | E18: =VLOOKUP(D18,'shipping inf'!B:D,2,FALSE) -> TP Hồ Chí Minh | F18: KH014 | G18: 90 | H18: 2410100601 | I18: D3001 | J18: 24 | K18: 12 | L18: Ban Giám Đốc | M18: Sanyo Minh Long | N18: =VLOOKUP(Table1[[#This Row],[elevator_traction_machine]],'Product inf'!A:B,2,FALSE) -> SP009 | O18: Kết cấu thép | P18: Tải khách | Q18: Sanotec Eco - Nhật Bản | R18: Sanotec DREAM control | S18: 325000000 | T18: 26000000 | U18: 351000000 | Y18: 4250000 | Z18: 45358 | AA18: D300132024
A19: 45724 | B19: 106/HĐ-2025 | C19: 541 đường nguyễn huệ, khóm 1, p.1, tp. sa đéc, đồng tháp | D19: Đồng Tháp | E19: =VLOOKUP(D19,'shipping inf'!B:D,2,FALSE) -> Đồng Tháp | F19: KH015 | G19: 90 | H19: 2510100601 | I19: D3001 | J19: 24 | K19: 12 | L19: Ban Giám Đốc | M19: Sanyo Minh Long | N19: =VLOOKUP(Table1[[#This Row],[elevator_traction_machine]],'Product inf'!A:B,2,FALSE) -> SP010 | O19: Bê tông | P19: Tải khách | Q19: Sanotec Eco - Trung Quốc | R19: Sanotec Eco control | S19: 447000000 | T19: 35760000 | U19: 482760000 | V19: 490500000 | Y19: 5670000 | Z19: 45734 | AA19: D300132025
A20: 46064 | B20: 106/HĐ-2026 | C20: 363/2/17 bình lợi, p.bình lợi trung, tphcm | D20: TP Hồ Chí Minh | E20: =VLOOKUP(D20,'shipping inf'!B:D,2,FALSE) -> TP Hồ Chí Minh | F20: KH016 | G20: 90 | H20: 2610100601 | I20: D3001 | J20: 24 | K20: 24 | L20: Ban Giám Đốc | M20: Sanyo Minh Long | N20: =VLOOKUP(Table1[[#This Row],[elevator_traction_machine]],'Product inf'!A:B,2,FALSE) -> SP006 | O20: Bê tông | P20: Tải khách | Q20: Sanotec - Nhật Bản | R20: Sanotec DREAM control | S20: 370000000 | U20: 370000000 | V20: 355500000 | X20: 6000000 | Z20: 46065 | AA20: D300122026
A21: 45365 | B21: 107/HĐ-2024 | C21: số 35 đường số 7, p. bình trưng đông. q.2, tp. hcm | D21: TP Hồ Chí Minh | E21: =VLOOKUP(D21,'shipping inf'!B:D,2,FALSE) -> TP Hồ Chí Minh | F21: KH017 | G21: 60 | H21: 2410100701 | I21: D3001 | J21: 24 | K21: 12 | L21: Ban Giám Đốc | M21: Sanyo Minh Long | N21: =VLOOKUP(Table1[[#This Row],[elevator_traction_machine]],'Product inf'!A:B,2,FALSE) -> SP006 | O21: Bê tông | P21: Tải khách | Q21: Sanotec - Nhật Bản | R21: Sanotec DREAM control | S21: 410000000 | U21: 410000000 | Y21: 5100000 | Z21: 45367 | AA21: D300132024
A22: 45721 | B22: 107/HĐ-2025 | C22: kdc cityland park hills, số 18 phan văn trị, p.10, q. gò vấp, tphcm | D22: TP Hồ Chí Minh | E22: =VLOOKUP(D22,'shipping inf'!B:D,2,FALSE) -> TP Hồ Chí Minh | F22: KH018 | G22: 90 | H22: 2510100701 | I22: D3001 | J22: 24 | K22: 12 | L22: Ban Giám Đốc | M22: Sanyo Minh Long | N22: =VLOOKUP(Table1[[#This Row],[elevator_traction_machine]],'Product inf'!A:B,2,FALSE) -> SP006 | O22: Bê tông | P22: Tải khách | Q22: Sanotec - Nhật Bản | R22: Sanotec DREAM control | S22: 400000000 | U22: 400000000 | V22: 386000000 | X22: 15000000 | Y22: 5500000 | Z22: 45722 | AA22: D300132025
A23: 46085 | B23: 107/HĐ-2026 | C23: số 18, đường b2, phường an khánh, tphcm | D23: TP Hồ Chí Minh | E23: =VLOOKUP(D23,'shipping inf'!B:D,2,FALSE) -> TP Hồ Chí Minh | F23: KH019 | G23: 50 | H23: 2610100701 | I23: D3001 | J23: 24 | K23: 24 | L23: Ban Giám Đốc | M23: Sanyo Minh Long | N23: =VLOOKUP(Table1[[#This Row],[elevator_traction_machine]],'Product inf'!A:B,2,FALSE) -> SP006 | O23: Kết cấu thép | P23: Tải khách | Q23: Sanotec - Nhật Bản | R23: Sanotec DREAM control | S23: 455000000 | T23: 36400000 | U23: 491400000 | V23: 441100000 | Z23: 46086 | AA23: D300132026
A24: 45369 | B24: 108/HĐ-2024 | C24: số 21 đường nguyễn tri phương, p. chánh nghĩa, tp. thủ dầu 1, bình dương | D24: Bình Dương | E24: =VLOOKUP(D24,'shipping inf'!B:D,2,FALSE) -> TP Hồ Chí Minh | F24: KH020 | G24: 60 | H24: 2410100801 | I24: D3001 | J24: 24 | K24: 12 | L24: Ban Giám Đốc | M24: Sanyo Minh Long | N24: =VLOOKUP(Table1[[#This Row],[elevator_traction_machine]],'Product inf'!A:B,2,FALSE) -> SP009 | O24: Bê tông | P24: Tải khách | Q24: Sanotec Eco - Nhật Bản | R24: Sanotec DREAM control | S24: 357500000 | U24: 357500000 | Y24: 4575000 | Z24: 45371 | AA24: D300132024
A25: 45793 | B25: 108/HĐ-2025 | C25: số 66m, võ văn kiệt, phường 9, tp vĩnh long, tỉnh vĩnh long | D25: Vĩnh Long | E25: =VLOOKUP(D25,'shipping inf'!B:D,2,FALSE) -> Vĩnh Long | F25: KH021 | G25: 90 | H25: 2510100801 | I25: D3001 | J25: 24 | K25: 12 | L25: Ban Giám Đốc | M25: Sanyo Minh Long | N25: =VLOOKUP(Table1[[#This Row],[elevator_traction_machine]],'Product inf'!A:B,2,FALSE) -> SP015 | O25: Bê tông | P25: Tải khách | Q25: Ziehl-Abegg - Đức | R25: Sanotec DREAM control | S25: 3.7037037e+08 | T25: 29629630 | U25: 4e+08 | V25: 393000000 | Y25: 4903704 | Z25: 45794 | AA25: D300152025
A26: 46088 | B26: 108/HĐ-2026 | C26: 27/19 huỳnh tịnh của, p.xuân hòa, tphcm | D26: TP Hồ Chí Minh | E26: =VLOOKUP(D26,'shipping inf'!B:D,2,FALSE) -> TP Hồ Chí Minh | F26: KH022 | G26: 60 | H26: 2610100801 | I26: D3001 | J26: 24 | K26: 24 | L26: Ban Giám Đốc | M26: Sanyo Minh Long | N26: =VLOOKUP(Table1[[#This Row],[elevator_traction_machine]],'Product inf'!A:B,2,FALSE) -> SP006 | O26: Kết cấu thép | P26: Tải khách | Q26: Sanotec - Nhật Bản | R26: Sanotec DREAM control | S26: 459000000 | U26: 459000000 | V26: 457000000 | Z26: 46090 | AA26: D300132026
A27: 45408 | B27: 109/HĐ-2024 | C27: 31/30/6 lê lai, p.3, q. gò vấp, tp. hcm (p1) | D27: TP Hồ Chí Minh | E27: =VLOOKUP(D27,'shipping inf'!B:D,2,FALSE) -> TP Hồ Chí Minh | F27: KH023 | G27: 60 | H27: 2410100901 | I27: D3001 | J27: 24 | K27: 12 | L27: Ban Giám Đốc | M27: Sanyo Minh Long | N27: =VLOOKUP(Table1[[#This Row],[elevator_traction_machine]],'Product inf'!A:B,2,FALSE) -> SP003 | O27: Bê tông | P27: Tải khách | Q27: Fuji Korea - Hàn Quốc | R27: Sanotec DREAM control | S27: 305000000 | U27: 305000000 | X27: 5000000 | Y27: 7100000 | Z27: 45418 | AA27: D300142024
A28: 45408 | B28: 109/HĐ-2024 | C28: 31/30/8 lê lai, p.3, q. gò vấp, tp. hcm (p2) | D28: TP Hồ Chí Minh | E28: =VLOOKUP(D28,'shipping inf'!B:D,2,FALSE) -> TP Hồ Chí Minh | F28: KH023 | G28: 60 | H28: 2410100902 | I28: D3001 | J28: 24 | K28: 12 | L28: Ban Giám Đốc | M28: Sanyo Minh Long | N28: =VLOOKUP(Table1[[#This Row],[elevator_traction_machine]],'Product inf'!A:B,2,FALSE) -> SP003 | O28: Bê tông | P28: Tải khách | Q28: Fuji Korea - Hàn Quốc | R28: Sanotec DREAM control | S28: 305000000 | U28: 305000000 | Z28: 45418 | AA28: D300142024
A29: 45734 | B29: 109/HĐ-2025 | C29: nhà số 6, ngõ 658 trương định, tổ 8, p. giáp bát, q. hoàng mai, hà nội | D29: Hà Nội | E29: =VLOOKUP(D29,'shipping inf'!B:D,2,FALSE) -> Hà Nội | F29: KH024 | G29: 90 | H29: 2510100901 | I29: D3001 | J29: 24 | K29: 12 | L29: Ban Giám Đốc | M29: Sanyo Minh Long | N29: =VLOOKUP(Table1[[#This Row],[elevator_traction_machine]],'Product inf'!A:B,2,FALSE) -> SP011 | O29: Bê tông | P29: Tải khách | Q29: Sanotec HP - Trung Quốc | R29: Sanotec Thuỷ lực control | S29: 330000000 | U29: 330000000 | V29: 245000000 | Y29: 4800000 | Z29: 45736 | AA29: D300132025
A30: 46100 | B30: 109/HĐ-2026 | C30: số 5 hẻm 9 đường số 66, phường an khánh, tphcm | D30: TP Hồ Chí Minh | E30: =VLOOKUP(D30,'shipping inf'!B:D,2,FALSE) -> TP Hồ Chí Minh | F30: KH025 | G30: 60 | H30: 2610100901 | I30: D3001 | J30: 24 | K30: 24 | L30: Ban Giám Đốc | M30: Sanyo Minh Long | N30: =VLOOKUP(Table1[[#This Row],[elevator_traction_machine]],'Product inf'!A:B,2,FALSE) -> SP015 | O30: Bê tông | P30: Tải khách | Q30: Ziehl-Abegg - Đức | R30: Sanotec DREAM control | S30: 407000000 | T30: 32560000 | U30: 439560000 | V30: 383000000 | Z30: 46100 | AA30: D300132026
A31: 45406 | B31: 110/HĐ-2024 | C31: nhà số 42, đường phạm ngọc thạch, p.9. tp. vũng tàu, bà rịa - vũng tàu | D31: Bà Rịa – Vũng Tàu | E31: =VLOOKUP(D31,'shipping inf'!B:D,2,FALSE) -> TP Hồ Chí Minh | F31: KH026 | G31: 60 | H31: 2410101001 | I31: D3001 | J31: 24 | K31: 12 | L31: Ban Giám Đốc | M31: Sanyo Minh Long | N31: =VLOOKUP(Table1[[#This Row],[elevator_traction_machine]],'Product inf'!A:B,2,FALSE) -> SP009 | O31: Kết cấu thép | P31: Tải khách | Q31: Sanotec Eco - Nhật Bản | R31: Sanotec DREAM control | S31: 390000000 | U31: 390000000 | Y31: 4900000 | Z31: 45414 | AA31: D300142024
A32: 45762 | B32: 110/HĐ-2025 | C32: 113/79/1 trần văn đang, phường 11, quận 3, tphcm | D32: TP Hồ Chí Minh | E32: =VLOOKUP(D32,'shipping inf'!B:D,2,FALSE) -> TP Hồ Chí Minh | F32: KH027 | G32: 180 | H32: 2510101001 | I32: D3001 | J32: 24 | K32: 24 | L32: MKT Đối tác | M32: Sanyo Minh Long | N32: =VLOOKUP(Table1[[#This Row],[elevator_traction_machine]],'Product inf'!A:B,2,FALSE) -> SP006 | O32: Bê tông | P32: Tải khách | Q32: Sanotec - Nhật Bản | R32: Sanotec DREAM control | S32: 372000000 | U32: 372000000 | V32: 391000000 | X32: 25000000 | Y32: 4920000 | Z32: 45762 | AA32: D300142025
A33: 46099 | B33: 110/HĐ-2026 | C33: lô sth 23-02 đường số 3, kdt mới lê hồng phong ii, p.nam nha trang, khánh hòa | D33: Khánh Hòa | E33: =VLOOKUP(D33,'shipping inf'!B:D,2,FALSE) -> Khánh Hòa | F33: KH028 | G33: 75 | H33: 2610101001 | I33: D3001 | J33: 24 | K33: 24 | L33: Ban Giám Đốc | M33: Sanyo Minh Long | N33: =VLOOKUP(Table1[[#This Row],[elevator_traction_machine]],'Product inf'!A:B,2,FALSE) -> SP005 | O33: Bê tông | P33: Tải khách | Q33: Sanotec - Eco Trung Quốc | R33: Sanotec Eco control | S33: 335000000 | U33: 335000000 | V33: 335000000 | Z33: 46100 | AA33: D300132026
A34: 45294 | B34: 1101/HĐ-2024 | C34: 88 đường b13 nguyễn hữu thọ, phước kiển, nhơn đức, nhà bè, tp. hcm | D34: TP Hồ Chí Minh | E34: =VLOOKUP(D34,'shipping inf'!B:D,2,FALSE) -> TP Hồ Chí Minh | F34: KH029 | G34: 60 | H34: 2411100101 | I34: D2001 | J34: 24 | K34: 24 | L34: MKT Cơ bản | M34: Sanyo Minh Long | N34: =VLOOKUP(Table1[[#This Row],[elevator_traction_machine]],'Product inf'!A:B,2,FALSE) -> SP015 | O34: Bê tông | P34: Tải khách | Q34: Ziehl-Abegg - Đức | R34: Sanotec DREAM control | S34: 373000000 | U34: 373000000 | V34: 381500000 | X34: 12000000 | Y34: 6000000 | Z34: 45295 | AA34: D200112024
A35: 45715 | B35: 1101/HĐ-2025 | C35: 815 lạc long quân, p.10, q. tân bình, tphcm | D35: TP Hồ Chí Minh | E35: =VLOOKUP(D35,'shipping inf'!B:D,2,FALSE) -> TP Hồ Chí Minh | F35: KH030 | G35: 180 | H35: 2511100101 | I35: D2001 | J35: 24 | K35: 36 | L35: Sales MQH cá nhân | M35: Sanyo Minh Long | N35: =VLOOKUP(Table1[[#This Row],[elevator_traction_machine]],'Product inf'!A:B,2,FALSE) -> SP015 | O35: Bê tông | P35: Tải khách | Q35: Ziehl-Abegg - Đức | R35: Sanotec DREAM control | S35: 436000000 | U35: 436000000 | V35: 445510000 | X35: 0 | Y35: 6000000 | Z35: 45716 | AA35: D200122025
A36: 45358 | B36: 1102/HĐ-2024 | C36: đội 3, thôn phan xá, x. xuân thủy, h. lệ thủy, quảng bình | D36: Quảng Bình | E36: =VLOOKUP(D36,'shipping inf'!B:D,2,FALSE) -> Quảng Trị | F36: KH031 | G36: 90 | H36: 2411100201 | I36: D2001 | J36: 24 | K36: 12 | L36: Sales MQH cá nhân | M36: Sanyo Minh Long | N36: =VLOOKUP(Table1[[#This Row],[elevator_traction_machine]],'Product inf'!A:B,2,FALSE) -> SP009 | O36: Bê tông | P36: Tải khách | Q36: Sanotec Eco - Nhật Bản | R36: Sanotec DREAM control | S36: 323400000 | U36: 323400000 | Y36: 6000000 | Z36: 45372 | AA36: D200132024
A37: 45761 | B37: 1102/HĐ-2025 | C37: 189 nguyễn trọng tuyển, phường 8, quận phú nhuận, tphcm | D37: TP Hồ Chí Minh | E37: =VLOOKUP(D37,'shipping inf'!B:D,2,FALSE) -> TP Hồ Chí Minh | F37: KH032 | G37: 540 | H37: 2511100201 | I37: D2001 | J37: 24 | K37: 24 | L37: MKT Đối tác | M37: Sanyo Minh Long | N37: =VLOOKUP(Table1[[#This Row],[elevator_traction_machine]],'Product inf'!A:B,2,FALSE) -> SP015 | O37: Bê tông | P37: Tải khách | Q37: Ziehl-Abegg - Đức | R37: Sanotec DREAM control | S37: 456000000 | U37: 456000000 | V37: 475000000 | X37: 25000000 | Y37: 6000000 | Z37: 45761 | AA37: D200142025
A38: 45390 | B38: 1103/HĐ-2024 | C38: lô 50, 51 ktđc ngô gia khảm, p. trà bá, tp. plei ku, gia lai | D38: Gia Lai | E38: =VLOOKUP(D38,'shipping inf'!B:D,2,FALSE) -> Gia Lai | F38: KH033 | G38: 60 | H38: 2411100301 | I38: D2001 | J38: 24 | K38: 24 | L38: Sales MQH cá nhân | M38: Sanyo Minh Long | N38: =VLOOKUP(Table1[[#This Row],[elevator_traction_machine]],'Product inf'!A:B,2,FALSE) -> SP015 | O38: Bê tông | P38: Tải khách | Q38: Ziehl-Abegg - Đức | R38: Sanotec DREAM control | S38: 380000000 | U38: 380000000 | V38: 394000000 | X38: 6000000 | Y38: 6000000 | Z38: 45392 | AA38: D200142024
A39: 45742 | B39: 1103/HĐ-2025 | C39: thửa 1088, tờ số 01, p. thạnh mỹ lợi, tp. thủ đức, tp. hcm | D39: TP Hồ Chí Minh | E39: =VLOOKUP(D39,'shipping inf'!B:D,2,FALSE) -> TP Hồ Chí Minh | F39: KH034 | G39: 150 | H39: 2511100301 | I39: D2001 | J39: 24 | K39: 24 | L39: Sales MQH cá nhân | M39: Sanyo Minh Long | N39: =VLOOKUP(Table1[[#This Row],[elevator_traction_machine]],'Product inf'!A:B,2,FALSE) -> SP001 | O39: Bê tông | P39: Tải khách | Q39: Belt - Nhật Bản | R39: Sanotec DREAM control | S39: 415000000 | U39: 415000000 | V39: 429000000 | X39: 10000000 | Y39: 6000000 | Z39: 45742 | AA39: D200132025
A40: 45504 | B40: 1104/HĐ-2024 | C40: 451/7 tô hiến thành, p.14, q.10, tp. hcm | D40: TP Hồ Chí Minh | E40: =VLOOKUP(D40,'shipping inf'!B:D,2,FALSE) -> TP Hồ Chí Minh | F40: KH035 | G40: 120 | H40: 2411100401 | I40: D2001 | J40: 24 | K40: 24 | L40: Sales MQH cá nhân | M40: Sanyo Minh Long | N40: =VLOOKUP(Table1[[#This Row],[elevator_traction_machine]],'Product inf'!A:B,2,FALSE) -> SP015 | O40: Bê tông | P40: Tải khách | Q40: Ziehl-Abegg - Đức | R40: Sanotec DREAM control | S40: 391000000 | U40: 391000000 | V40: 394000000 | X40: 25000000 | Y40: 6000000 | Z40: 45519 | AA40: D200172024
A41: 45757 | B41: 1104/HĐ-2025 | C41: 311 phước thiện, phường long bình, quận 9, tphcm | D41: TP Hồ Chí Minh | E41: =VLOOKUP(D41,'shipping inf'!B:D,2,FALSE) -> TP Hồ Chí Minh | F41: KH036 | G41: 90 | H41: 2511100401 | I41: D2001 | J41: 24 | K41: 24 | L41: MKT Cơ bản | M41: Sanyo Minh Long | N41: =VLOOKUP(Table1[[#This Row],[elevator_traction_machine]],'Product inf'!A:B,2,FALSE) -> SP006 | O41: Bê tông | P41: Tải khách | Q41: Sanotec - Nhật Bản | R41: Sanotec DREAM control | S41: 407400000 | T41: 32600000 | U41: 440000000 | V41: 416122000 | X41: 0 | Y41: 6000000 | Z41: 45758 | AA41: D200142025
A42: 45444 | B42: 1105/HĐ-2024 | C42: 641/2/1 quang trung, p.11, q. gò vấp, tp. hcm | D42: TP Hồ Chí Minh | E42: =VLOOKUP(D42,'shipping inf'!B:D,2,FALSE) -> TP Hồ Chí Minh | F42: KH037 | G42: 120 | H42: 2411100501 | I42: D2001 | J42: 24 | K42: 24 | L42: MKT Cơ bản | M42: Sanyo Minh Long | N42: =VLOOKUP(Table1[[#This Row],[elevator_traction_machine]],'Product inf'!A:B,2,FALSE) -> SP015 | O42: Bê tông | P42: Tải khách | Q42: Ziehl-Abegg - Đức | R42: Sanotec DREAM control | S42: 370000000 | U42: 370000000 | V42: 371500000 | X42: 20000000 | Y42: 6000000 | Z42: 45447 | AA42: D200162024
A43: 45782 | B43: 1105/HĐ-2025 | C43: 195/9/1 tôn thất thuyết, phường 3, quận 4, tphcm | D43: TP Hồ Chí Minh | E43: =VLOOKUP(D43,'shipping inf'!B:D,2,FALSE) -> TP Hồ Chí Minh | F43: KH038 | G43: 90 | H43: 2511100501 | I43: D2001 | J43: 24 | K43: 24 | L43: MKT Cơ bản | M43: Sanyo Minh Long | N43: =VLOOKUP(Table1[[#This Row],[elevator_traction_machine]],'Product inf'!A:B,2,FALSE) -> SP001 | O43: Bê tông | P43: Tải khách | Q43: Belt - Nhật Bản | R43: Sanotec DREAM control | S43: 352800000 | U43: 352800000 | V43: 352800000 | X43: 10000000 | Y43: 6000000 | Z43: 45782 | AA43: D200152025
A44: 45457 | B44: 1106/HĐ-2024 | C44: 32-34 đường 26, p. bình trị đông b, q. bình tân, tp. hcm | D44: TP Hồ Chí Minh | E44: =VLOOKUP(D44,'shipping inf'!B:D,2,FALSE) -> TP Hồ Chí Minh | F44: KH039 | G44: 75 | H44: 2411100601 | I44: D2001 | J44: 24 | K44: 24 | L44: MKT Cơ bản | M44: Sanyo Minh Long | N44: =VLOOKUP(Table1[[#This Row],[elevator_traction_machine]],'Product inf'!A:B,2,FALSE) -> SP015 | O44: Kết cấu thép | P44: Tải khách | Q44: Ziehl-Abegg - Đức | R44: Sanotec DREAM control | S44: 598000000 | U44: 598000000 | V44: 583060000 | X44: 35000000 | Y44: 6000000 | Z44: 45460 | AA44: D200162024
A45: 45475 | B45: 1107/HĐ-2024 | C45: 133/60/25 bình thành, p. bình hưng hòa b, q. bình tân, tp. hcm | D45: TP Hồ Chí Minh | E45: =VLOOKUP(D45,'shipping inf'!B:D,2,FALSE) -> TP Hồ Chí Minh | F45: KH040 | G45: 90 | H45: 2411100701 | I45: D2001 | J45: 24 | K45: 24 | L45: Sales MQH cá nhân | M45: Sanyo Minh Long | N45: =VLOOKUP(Table1[[#This Row],[elevator_traction_machine]],'Product inf'!A:B,2,FALSE) -> SP006 | O45: Bê tông | P45: Tải khách | Q45: Sanotec - Nhật Bản | R45: Sanotec DREAM control | S45: 326000000 | U45: 326000000 | V45: 346000000 | X45: 5000000 | Y45: 6000000 | Z45: 45484 | AA45: D200172024
A46: 45481 | B46: 1108/HĐ-2024 | C46: 357 kênh tân hóa, p. hòa thạnh, q. tân phú, tp. hcm | D46: TP Hồ Chí Minh | E46: =VLOOKUP(D46,'shipping inf'!B:D,2,FALSE) -> TP Hồ Chí Minh | F46: KH041 | G46: 150 | H46: 2411100801 | I46: D2001 | J46: 24 | K46: 24 | L46: MKT Cơ bản | M46: Sanyo Minh Long | N46: =VLOOKUP(Table1[[#This Row],[elevator_traction_machine]],'Product inf'!A:B,2,FALSE) -> SP015 | O46: Bê tông | P46: Tải khách | Q46: Ziehl-Abegg - Đức | R46: Sanotec DREAM control | S46: 410000000 | U46: 410000000 | V46: 435400000 | X46: 6000000 | Y46: 6000000 | Z46: 45486 | AA46: D200172024
A47: 45498 | B47: 1109/HĐ-2024 | C47: 98/39 cống lỡ, p.15, q. tân bình, tp.hcm | D47: TP Hồ Chí Minh | E47: =VLOOKUP(D47,'shipping inf'!B:D,2,FALSE) -> TP Hồ Chí Minh | F47: KH042 | G47: 54 | H47: 2411100901 | I47: D2001 | J47: 24 | K47: 24 | L47: Sales MQH cá nhân | M47: Sanyo Minh Long | N47: =VLOOKUP(Table1[[#This Row],[elevator_traction_machine]],'Product inf'!A:B,2,FALSE) -> SP006 | O47: Bê tông | P47: Tải khách | Q47: Sanotec - Nhật Bản | R47: Sanotec DREAM control | S47: 377000000 | U47: 377000000 | V47: 396450000 | Y47: 6000000 | Z47: 45500 | AA47: D200172024
A48: 45416 | B48: 111/HĐ-2024 | C48: evn hòa bình, p. tân thịnh, tp. hòa bình, hòa bình | D48: Hòa Bình | E48: =VLOOKUP(D48,'shipping inf'!B:D,2,FALSE) -> Phú Thọ | F48: KH043 | G48: 100 | H48: 2410101101 | I48: D3001 | J48: 24 | K48: 12 | L48: Ban Giám Đốc | M48: Sanyo Minh Long | N48: =VLOOKUP(Table1[[#This Row],[elevator_traction_machine]],'Product inf'!A:B,2,FALSE) -> SP006 | O48: Bê tông | P48: Tải hàng | Q48: Sanotec - Nhật Bản | R48: Sanotec DREAM control | S48: 603000000 | T48: 48240000 | U48: 651240000 | X48: 80000000 | Y48: 7030000 | Z48: 45421 | AA48: D300152024
A49: 45736 | B49: 111/HĐ-2025 | C49: 190/2 trần quốc tuấn, p.4, tp. bến tre, bến tre | D49: Vĩnh Long | E49: =VLOOKUP(D49,'shipping inf'!B:D,2,FALSE) -> Vĩnh Long | F49: KH044 | G49: 75 | H49: 2510101101 | I49: D3001 | J49: 24 | K49: 12 | L49: Ban Giám Đốc | M49: Sanyo Minh Long | N49: =VLOOKUP(Table1[[#This Row],[elevator_traction_machine]],'Product inf'!A:B,2,FALSE) -> SP006 | O49: Bê tông | P49: Tải khách | Q49: Sanotec - Nhật Bản | R49: Sanotec DREAM control | S49: 360000000 | T49: 28800000 | U49: 388800000 | V49: 384620000 | X49: 0 | Y49: 4800000 | Z49: 45736 | AA49: D300132025
A50: 45505 | B50: 1110/HĐ-2024 | C50: thửa 584, tbđ số 43, p. an lạc a, q. bình tân, tp. hcm (p1) | D50: TP Hồ Chí Minh | E50: =VLOOKUP(D50,'shipping inf'!B:D,2,FALSE) -> TP Hồ Chí Minh | F50: KH045 | G50: 75 | H50: 2411101001 | I50: D2001 | J50: 24 | K50: 24 | L50: MKT Cơ bản | M50: Sanyo Minh Long | N50: =VLOOKUP(Table1[[#This Row],[elevator_traction_machine]],'Product inf'!A:B,2,FALSE) -> SP006 | O50: Bê tông | P50: Tải khách | Q50: Sanotec - Nhật Bản | R50: Sanotec DREAM control | S50: 330000000 | U50: 330000000 | V50: 669600000 | X50: 40000000 | Y50: 12000000 | Z50: 45505 | AA50: D200182024
A51: 45505 | B51: 1110/HĐ-2024 | C51: thửa 584, tbđ số 43, p. an lạc a, q. bình tân, tp. hcm (p2) | D51: TP Hồ Chí Minh | E51: =VLOOKUP(D51,'shipping inf'!B:D,2,FALSE) -> TP Hồ Chí Minh | F51: KH045 | G51: 75 | H51: 2411101002 | I51: D2001 | J51: 24 | K51: 24 | L51: MKT Cơ bản | M51: Sanyo Minh Long | N51: =VLOOKUP(Table1[[#This Row],[elevator_traction_machine]],'Product inf'!A:B,2,FALSE) -> SP006 | O51: Bê tông | P51: Tải khách | Q51: Sanotec - Nhật Bản | R51: Sanotec DREAM control | S51: 330000000 | U51: 330000000 | V51: 669600000 | Z51: 45505 | AA51: D200182024
A52: 45517 | B52: 1111/HĐ-2024 | C52: lô i8 kdc thới an, p. thới an, q.12, tp. hcm | D52: TP Hồ Chí Minh | E52: =VLOOKUP(D52,'shipping inf'!B:D,2,FALSE) -> TP Hồ Chí Minh | F52: KH046 | G52: 90 | H52: 2411101101 | I52: D2001 | J52: 24 | K52: 24 | L52: MKT Cơ bản | M52: Sanyo Minh Long | N52: =VLOOKUP(Table1[[#This Row],[elevator_traction_machine]],'Product inf'!A:B,2,FALSE) -> SP015 | O52: Bê tông | P52: Tải khách | Q52: Ziehl-Abegg - Đức | R52: Sanotec DREAM control | S52: 354000000 | U52: 354000000 | V52: 361954000 | X52: 20000000 | Y52: 6000000 | Z52: 45517 | AA52: D200182024
A53: 45532 | B53: 1112/HĐ-2024 | C53: 506 phan văn trị, p.7, q.5, tp. hcm | D53: TP Hồ Chí Minh | E53: =VLOOKUP(D53,'shipping inf'!B:D,2,FALSE) -> TP Hồ Chí Minh | F53: KH047 | G53: 120 | H53: 2411101201 | I53: D2001 | J53: 24 | K53: 24 | L53: MKT Cơ bản | M53: Sanyo Minh Long | N53: =VLOOKUP(Table1[[#This Row],[elevator_traction_machine]],'Product inf'!A:B,2,FALSE) -> SP006 | O53: Kết cấu thép | P53: Tải khách | Q53: Sanotec - Nhật Bản | R53: Sanotec DREAM control | S53: 658000000 | U53: 658000000 | V53: 663450000 | X53: 25000000 | Y53: 6000000 | Z53: 45532 | AA53: D200182024
A54: 45582 | B54: 1114/HĐ-2024 | C54: 611/7 lê quang định, p.1, q. gò vấp, tp. hcm | D54: TP Hồ Chí Minh | E54: =VLOOKUP(D54,'shipping inf'!B:D,2,FALSE) -> TP Hồ Chí Minh | F54: KH048 | G54: 60 | H54: 2411101401 | I54: D2001 | J54: 24 | K54: 24 | L54: MKT Cơ bản | M54: Sanyo Minh Long | N54: =VLOOKUP(Table1[[#This Row],[elevator_traction_machine]],'Product inf'!A:B,2,FALSE) -> SP015 | O54: Bê tông | P54: Tải khách | Q54: Ziehl-Abegg - Đức | R54: Sanotec DREAM control | S54: 395000000 | U54: 395000000 | V54: 405100000 | X54: 5000000 | Y54: 6000000 | Z54: 45582 | AA54: D2001102024
A55: 45581 | B55: 1115/HĐ-2024 | C55: thửa 322, tờ 17, suối hội phú, p. hội thương, tp. pleiku, gia lai | D55: Gia Lai | E55: =VLOOKUP(D55,'shipping inf'!B:D,2,FALSE) -> Gia Lai | F55: KH049 | G55: 75 | H55: 2411101501 | I55: D2001 | J55: 24 | K55: 24 | L55: MKT Cơ bản | M55: Sanyo Minh Long | N55: =VLOOKUP(Table1[[#This Row],[elevator_traction_machine]],'Product inf'!A:B,2,FALSE) -> SP006 | O55: Bê tông | P55: Tải khách | Q55: Sanotec - Nhật Bản | R55: Sanotec DREAM control | S55: 405000000 | U55: 405000000 | V55: 418723500 | X55: 8000000 | Y55: 6000000 | Z55: 45582 | AA55: D2001102024
A56: 45587 | B56: 1116/HĐ-2024 | C56: căn d-lk.56-21 t&t, long hậu, h cần giuộc, long an | D56: Long An | E56: =VLOOKUP(D56,'shipping inf'!B:D,2,FALSE) -> Tây Ninh | F56: KH050 | G56: 75 | H56: 2411101601 | I56: D2001 | J56: 24 | K56: 24 | L56: Sales MQH cá nhân | M56: Sanyo Minh Long | N56: =VLOOKUP(Table1[[#This Row],[elevator_traction_machine]],'Product inf'!A:B,2,FALSE) -> SP006 | O56: Bê tông | P56: Tải khách | Q56: Sanotec - Nhật Bản | R56: Sanotec DREAM control | S56: 360000000 | U56: 360000000 | V56: 365000000 | X56: 8000000 | Y56: 6000000 | Z56: 45588 | AA56: D2001102024
A57: 45609 | B57: 1117/HĐ-2024 | C57: 256 ba đình, p.10, q.8, tp. hcm | D57: TP Hồ Chí Minh | E57: =VLOOKUP(D57,'shipping inf'!B:D,2,FALSE) -> TP Hồ Chí Minh | F57: KH051 | G57: 360 | H57: 2411101701 | I57: D2001 | J57: 24 | K57: 24 | L57: MKT Cơ bản | M57: Sanyo Minh Long | N57: =VLOOKUP(Table1[[#This Row],[elevator_traction_machine]],'Product inf'!A:B,2,FALSE) -> SP006 | O57: Bê tông | P57: Tải khách | Q57: Sanotec - Nhật Bản | R57: Sanotec DREAM control | S57: 348500000 | U57: 348500000 | V57: 374500000 | Y57: 6000000 | Z57: 45610 | AA57: D2001112024
A58: 45435 | B58: 112/HĐ-2024 | C58: 105/35 lê sát, p. tân quý, q. tân phú, tp. hcm | D58: TP Hồ Chí Minh | E58: =VLOOKUP(D58,'shipping inf'!B:D,2,FALSE) -> TP Hồ Chí Minh | F58: KH052 | G58: 90 | H58: 2410101201 | I58: D3001 | J58: 24 | K58: 12 | L58: Ban Giám Đốc | M58: Sanyo Minh Long | N58: =VLOOKUP(Table1[[#This Row],[elevator_traction_machine]],'Product inf'!A:B,2,FALSE) -> SP006 | O58: Bê tông | P58: Tải khách | Q58: Sanotec - Nhật Bản | R58: Sanotec DREAM control | S58: 360000000 | U58: 360000000 | Y58: 4600000 | Z58: 45437 | AA58: D300152024
A59: 45744 | B59: 112/HĐ-2025 | C59: chùa pháp hoa, 16 chu văn an, phường nghĩa thành, gia nghĩa, đắk nông | D59: Lâm Đồng | E59: =VLOOKUP(D59,'shipping inf'!B:D,2,FALSE) -> Lâm Đồng | F59: KH053 | G59: 75 | H59: 2510111201 | I59: D3001 | J59: 24 | K59: 12 | L59: Ban Giám Đốc | M59: Sanyo Minh Long | N59: =VLOOKUP(Table1[[#This Row],[elevator_traction_machine]],'Product inf'!A:B,2,FALSE) -> SP010 | O59: Bê tông | P59: Tải khách | Q59: Sanotec Eco - Trung Quốc | R59: Sanotec Eco control | S59: 335000000 | U59: 335000000 | V59: 363000000 | Y59: 4550000 | Z59: 45744 | AA59: D300132025
A60: 45443 | B60: 114/HĐ-2024 | C60: nhà c41 kdc caric, p. bình an, tp. thủ đức, tp. hcm | D60: TP Hồ Chí Minh | E60: =VLOOKUP(D60,'shipping inf'!B:D,2,FALSE) -> TP Hồ Chí Minh | F60: KH054 | G60: 90 | H60: 2410101401 | I60: D3001 | J60: 36 | K60: 36 | L60: Ban Giám Đốc | M60: Sanyo Minh Long | N60: =VLOOKUP(Table1[[#This Row],[elevator_traction_machine]],'Product inf'!A:B,2,FALSE) -> SP015 | O60: Bê tông | P60: Tải khách | Q60: Ziehl-Abegg - Đức | R60: Sanotec DREAM control | S60: 499000000 | U60: 499000000 | Y60: 5990000 | Z60: 45460 | AA60: D300152024
A61: 45768 | B61: 114/HĐ-2025 | C61: m4 đường thất sơn, cư xá bắc hải, quận 10, tphcm | D61: TP Hồ Chí Minh | E61: =VLOOKUP(D61,'shipping inf'!B:D,2,FALSE) -> TP Hồ Chí Minh | F61: KH055 | G61: 60 | H61: 2510101401 | I61: D3001 | J61: 24 | K61: 12 | L61: Ban Giám Đốc | M61: Sanyo Minh Long | N61: =VLOOKUP(Table1[[#This Row],[elevator_traction_machine]],'Product inf'!A:B,2,FALSE) -> SP006 | O61: Bê tông | P61: Tải khách | Q61: Sanotec - Nhật Bản | R61: Sanotec DREAM control | S61: 390000000 | U61: 390000000 | V61: 382000000 | Z61: 45768 | AA61: D300142025
A62: 45439 | B62: 115/HĐ-2024 | C62: số nhà 209 khổng tử, p. xuân trung, tp. long khánh, đồng nai | D62: Đồng Nai | E62: =VLOOKUP(D62,'shipping inf'!B:D,2,FALSE) -> Đồng Nai | F62: KH056 | G62: 120 | H62: 2410101501 | I62: D3001 | J62: 24 | K62: 24 | L62: Ban Giám Đốc | M62: Sanyo Minh Long | N62: =VLOOKUP(Table1[[#This Row],[elevator_traction_machine]],'Product inf'!A:B,2,FALSE) -> SP006 | O62: Bê tông | P62: Tải khách | Q62: Sanotec - Nhật Bản | R62: Sanotec DREAM control | S62: 348000000 | U62: 348000000 | Y62: 4480000 | Z62: 45440 | AA62: D300152024
A63: 45748 | B63: 115/HĐ-2025 | C63: 381/11 lê văn quới, p. bình trị đông a, q. bình tân, tphcm | D63: TP Hồ Chí Minh | E63: =VLOOKUP(D63,'shipping inf'!B:D,2,FALSE) -> TP Hồ Chí Minh | F63: KH057 | G63: 120 | H63: 2510101501 | I63: D3001 | J63: 24 | K63: 12 | L63: Ban Giám Đốc | M63: Sanyo Minh Long | N63: =VLOOKUP(Table1[[#This Row],[elevator_traction_machine]],'Product inf'!A:B,2,FALSE) -> SP006 | O63: Bê tông | P63: Tải khách | Q63: Sanotec - Nhật Bản | R63: Sanotec DREAM control | S63: 417000000 | U63: 417000000 | V63: 416800000 | X63: 15000000 | Y63: 5670000 | Z63: 45748 | AA63: D300142025
A64: 45455 | B64: 116/HĐ-2024 | C64: 11b-12b hùng vương, p. xuân trung, tp. long khánh, đồng nai | D64: Đồng Nai | E64: =VLOOKUP(D64,'shipping inf'!B:D,2,FALSE) -> Đồng Nai | F64: KH058 | G64: 90 | H64: 2410101601 | I64: D3001 | J64: 24 | K64: 12 | L64: Ban Giám Đốc | M64: Sanyo Minh Long | N64: =VLOOKUP(Table1[[#This Row],[elevator_traction_machine]],'Product inf'!A:B,2,FALSE) -> SP006 | O64: Bê tông | P64: Tải khách | Q64: Sanotec - Nhật Bản | R64: Sanotec DREAM control | S64: 416000000 | U64: 416000000 | Y64: 5160000 | Z64: 45457 | AA64: D300162024
A65: 45761 | B65: 116/HĐ-2025 | C65: 165 lê niệm, p. phú thạnh, q. tân phú, tphcm | D65: TP Hồ Chí Minh | E65: =VLOOKUP(D65,'shipping inf'!B:D,2,FALSE) -> TP Hồ Chí Minh | F65: KH059 | G65: 120 | H65: 2510101601 | I65: D3001 | J65: 24 | K65: 12 | L65: Ban Giám Đốc | M65: Sanyo Minh Long | N65: =VLOOKUP(Table1[[#This Row],[elevator_traction_machine]],'Product inf'!A:B,2,FALSE) -> SP006 | O65: Bê tông | P65: Tải khách | Q65: Sanotec - Nhật Bản | R65: Sanotec DREAM control | S65: 360000000 | U65: 360000000 | V65: 362200000 | X65: 0 | Y65: 4800000 | Z65: 45761 | AA65: D300142025
A66: 45468 | B66: 117/HĐ-2024 | C66: nhà máy giấy đồng tiến, lô a216-a217-a218, đường số 2, kcn thái hòa, ấp tân hòa, x. đức lập hạ, h. đức hòa, long an | D66: Long An | E66: =VLOOKUP(D66,'shipping inf'!B:D,2,FALSE) -> Tây Ninh | F66: KH060 | G66: 90 | H66: 2410101701 | I66: D3001 | J66: 24 | K66: 12 | L66: Ban Giám Đốc | M66: Sanyo Minh Long | N66: =VLOOKUP(Table1[[#This Row],[elevator_traction_machine]],'Product inf'!A:B,2,FALSE) -> SP007 | O66: Bê tông | P66: Tải hàng | Q66: Sanotec - Nidec | R66: Sanotec DREAM control | S66: 2636000000 | T66: 210880000 | U66: 2846880000 | Y66: 27360000 | Z66: 45476 | AA66: D300162024
A67: 45762 | B67: 117/HĐ-2025 | C67: thửa đất số 3, tờ bản đồ 20, p9, q.phú nhuận, tphcm | D67: TP Hồ Chí Minh | E67: =VLOOKUP(D67,'shipping inf'!B:D,2,FALSE) -> TP Hồ Chí Minh | F67: KH061 | G67: 120 | H67: 2510101701 | I67: D3001 | J67: 24 | K67: 12 | L67: Ban Giám Đốc | M67: Sanyo Minh Long | N67: =VLOOKUP(Table1[[#This Row],[elevator_traction_machine]],'Product inf'!A:B,2,FALSE) -> SP006 | O67: Bê tông | P67: Tải khách | Q67: Sanotec - Nhật Bản | R67: Sanotec DREAM control | S67: 335000000 | U67: 335000000 | V67: 330000000 | Y67: 4850000 | Z67: 45762 | AA67: D300142025
A68: 45799 | B68: 118/HĐ-2025 | C68: số 7, nguyễn văn đậu, phường 5, quận phú nhuận, tphcm | D68: TP Hồ Chí Minh | E68: =VLOOKUP(D68,'shipping inf'!B:D,2,FALSE) -> TP Hồ Chí Minh | F68: KH062 | G68: 90 | H68: 2510101801 | I68: D3001 | J68: 24 | K68: 12 | L68: Ban Giám Đốc | M68: Sanyo Minh Long | N68: =VLOOKUP(Table1[[#This Row],[elevator_traction_machine]],'Product inf'!A:B,2,FALSE) -> SP006 | O68: Bê tông | P68: Tải khách | Q68: Sanotec - Nhật Bản | R68: Sanotec DREAM control | S68: 370000000 | U68: 370000000 | V68: 386000000 | X68: 2000000 | Y68: 4900000 | Z68: 45799 | AA68: D300152025
A69: 45492 | B69: 119/HĐ-2024 | C69: dự án p&g 02, vsip ii-a, đường tân hiệp 17, p. vĩnh tân, q. tân uyên, bình dương | D69: Bình Dương | E69: =VLOOKUP(D69,'shipping inf'!B:D,2,FALSE) -> TP Hồ Chí Minh | F69: KH063 | G69: 90 | H69: 2410101901 | I69: D3001 | J69: 24 | K69: 12 | L69: Ban Giám Đốc | M69: Sanyo Minh Long | N69: =VLOOKUP(Table1[[#This Row],[elevator_traction_machine]],'Product inf'!A:B,2,FALSE) -> SP006 | O69: Bê tông | P69: Tải khách | Q69: Sanotec - Nhật Bản | R69: Sanotec DREAM control | S69: 561180000 | T69: 44894400 | U69: 606074400 | V69: 422000000 | X69: 20000000 | Y69: 1561180 | Z69: 45520 | AA69: D300172024
A70: 45771 | B70: 119/HĐ-2025 | C70: 90 ql57, tt. thạnh phú, thạnh phú, bến tre | D70: Vĩnh Long | E70: =VLOOKUP(D70,'shipping inf'!B:D,2,FALSE) -> Vĩnh Long | F70: KH064 | G70: 40 | H70: 2510101901 | I70: D3001 | J70: 24 | K70: 12 | L70: Ban Giám Đốc | M70: Sanyo Minh Long | N70: =VLOOKUP(Table1[[#This Row],[elevator_traction_machine]],'Product inf'!A:B,2,FALSE) -> SP006 | O70: Bê tông | P70: Tải khách | Q70: Sanotec - Nhật Bản | R70: Sanotec DREAM control | S70: 361000000 | U70: 361000000 | V70: 371000000 | Y70: 4810000 | Z70: 45771 | AA70: D300142025
A71: 45495 | B71: 120/HĐ-2024 | C71: hội dòng mến thánh giá gò vấp, 523a đường lê đức thọ, p.16, q. gò vấp, tp. hcm | D71: TP Hồ Chí Minh | E71: =VLOOKUP(D71,'shipping inf'!B:D,2,FALSE) -> TP Hồ Chí Minh | F71: KH065 | G71: 90 | H71: 2410102001 | I71: D3001 | J71: 36 | K71: 24 | L71: Ban Giám Đốc | M71: Sanyo Minh Long | N71: =VLOOKUP(Table1[[#This Row],[elevator_traction_machine]],'Product inf'!A:B,2,FALSE) -> SP008 | O71: Kết cấu thép | P71: Tải khách | Q71: Sanotec - Trung Quốc | R71: Sanotec DREAM control | S71: 370000000 | U71: 370000000 | Y71: 4700000 | Z71: 45496 | AA71: D300172024
A72: 45986 | B72: 120/HĐ-2025 | C72: số 40 đường cửu long, p.tân bình, tphcm | D72: TP Hồ Chí Minh | E72: =VLOOKUP(D72,'shipping inf'!B:D,2,FALSE) -> TP Hồ Chí Minh | F72: KH066 | G72: 90 | H72: 2510102001 | I72: D3001 | J72: 24 | K72: 12 | L72: Ban Giám Đốc | M72: Sanyo Minh Long | N72: =VLOOKUP(Table1[[#This Row],[elevator_traction_machine]],'Product inf'!A:B,2,FALSE) -> SP006 | O72: Bê tông | P72: Tải khách | Q72: Sanotec - Nhật Bản | R72: Sanotec DREAM control | S72: 425000000 | U72: 425000000 | V72: 447400000 | Y72: 5450000 | Z72: 45986 | AA72: D3001112025
A73: 45511 | B73: 1201/HĐ-2024 | C73: nhà số 5 đường số 86, p.10, q.6, tp. hcm | D73: TP Hồ Chí Minh | E73: =VLOOKUP(D73,'shipping inf'!B:D,2,FALSE) -> TP Hồ Chí Minh | F73: KH067 | G73: 45 | H73: 2411200101 | I73: D2006 | J73: 24 | K73: 24 | L73: MKT Cơ bản | M73: Sanyo Minh Long | N73: =VLOOKUP(Table1[[#This Row],[elevator_traction_machine]],'Product inf'!A:B,2,FALSE) -> SP015 | O73: Bê tông | P73: Tải khách | Q73: Ziehl-Abegg - Đức | R73: Sanotec DREAM control | S73: 423800000 | T73: 33904000 | U73: 457704000 | V73: 405800000 | X73: 25000000 | Y73: 6000000 | Z73: 45514 | AA73: D200682024
A74: 45666 | B74: 1201/HĐ-2025 | C74: 200/19 bình lợi, p.13, q. bình thạnh, tphcm | D74: TP Hồ Chí Minh | E74: =VLOOKUP(D74,'shipping inf'!B:D,2,FALSE) -> TP Hồ Chí Minh | F74: KH068 | G74: 90 | H74: 2511200101 | I74: D2006 | J74: 24 | K74: 24 | L74: Sales MQH cá nhân | M74: Sanyo Minh Long | N74: =VLOOKUP(Table1[[#This Row],[elevator_traction_machine]],'Product inf'!A:B,2,FALSE) -> SP015 | O74: Bê tông | P74: Tải khách | Q74: Ziehl-Abegg - Đức | R74: Sanotec DREAM control | S74: 431600000 | T74: 34528000 | U74: 466128000 | V74: 439600000 | X74: 30000000 | Y74: 6000000 | Z74: 45666 | AA74: D200612025
A75: 46057 | B75: 1201/HĐ-2026 | C75: biệt thự r75 dự án grand bay hạ long villas - lagoon residences, quảg ninh, việt nam | D75: Quảng Ninh | E75: =VLOOKUP(D75,'shipping inf'!B:D,2,FALSE) -> Quảng Ninh | F75: KH069 | G75: 90 | H75: 2611200101 | I75: D2006 | J75: 24 | K75: 24 | L75: Sales MQH cá nhân | M75: Sanyo Minh Long | N75: =VLOOKUP(Table1[[#This Row],[elevator_traction_machine]],'Product inf'!A:B,2,FALSE) -> SP006 | O75: Bê tông | P75: Tải khách | Q75: Sanotec - Nhật Bản | R75: Sanotec DREAM control | S75: 391200000 | U75: 391200000 | V75: 391700000 | X75: 20000000 | Y75: 10000000 | Z75: 46057 | AA75: D200622026
A76: 45500 | B76: 1202/HĐ-2024 | C76: 26 đường số 1, p. phú mỹ, q.7, tp.hcm | D76: TP Hồ Chí Minh | E76: =VLOOKUP(D76,'shipping inf'!B:D,2,FALSE) -> TP Hồ Chí Minh | F76: KH070 | G76: 90 | H76: 2411200201 | I76: D2006 | J76: 24 | K76: 24 | L76: MKT Cơ bản | M76: Sanyo Minh Long | N76: =VLOOKUP(Table1[[#This Row],[elevator_traction_machine]],'Product inf'!A:B,2,FALSE) -> SP015 | O76: Kết cấu thép | P76: Tải khách | Q76: Ziehl-Abegg - Đức | R76: Sanotec DREAM control | S76: 544900000 | U76: 544900000 | V76: 531400000 | X76: 25000000 | Y76: 8000000 | Z76: 45500 | AA76: D200672024
A77: 45502 | B77: 1203/HĐ-2024 | C77: số l03 khu nhà ở phú hữu, tp. thủ đức, tp. hcm | D77: TP Hồ Chí Minh | E77: =VLOOKUP(D77,'shipping inf'!B:D,2,FALSE) -> TP Hồ Chí Minh | F77: KH071 | G77: 75 | H77: 2411200301 | I77: D2006 | J77: 24 | K77: 24 | L77: Sales MQH cá nhân | M77: Sanyo Minh Long | N77: =VLOOKUP(Table1[[#This Row],[elevator_traction_machine]],'Product inf'!A:B,2,FALSE) -> SP015 | O77: Bê tông | P77: Tải khách | Q77: Ziehl-Abegg - Đức | R77: Sanotec DREAM control | S77: 404000000 | U77: 404000000 | X77: 30000000 | Y77: 6000000 | Z77: 45503 | AA77: D200672024
A78: 45900 | B78: 1203/HĐ-2025 | C78: 553/2/14 lũy bán bích, p.phú thạnh, q.tân phú,tphcm | D78: TP Hồ Chí Minh | E78: =VLOOKUP(D78,'shipping inf'!B:D,2,FALSE) -> TP Hồ Chí Minh | F78: KH072 | G78: 90 | H78: 2511200301 | I78: D2006 | J78: 24 | K78: 24 | L78: MKT Đối tác | M78: Sanyo Minh Long | N78: =VLOOKUP(Table1[[#This Row],[elevator_traction_machine]],'Product inf'!A:B,2,FALSE) -> SP006 | O78: Bê tông | P78: Tải khách | Q78: Sanotec - Nhật Bản | R78: Sanotec DREAM control | S78: 363000000 | U78: 363000000 | V78: 379000000 | X78: 25000000 | Y78: 6000000 | Z78: 45912 | AA78: D200682025
A79: 45491 | B79: 1204/HĐ-2024 | C79: 50 đường số 9, p.16, q. gò vấp, tp. hcm (hđ thanh lý) | D79: TP Hồ Chí Minh | E79: =VLOOKUP(D79,'shipping inf'!B:D,2,FALSE) -> TP Hồ Chí Minh | F79: KH073 | G79: 120 | H79: 2411200401 | I79: D2006 | J79: 24 | K79: 24 | L79: Sales MQH cá nhân | M79: Sanyo Minh Long | N79: =VLOOKUP(Table1[[#This Row],[elevator_traction_machine]],'Product inf'!A:B,2,FALSE) -> SP015 | O79: Bê tông | P79: Tải khách | Q79: Ziehl-Abegg - Đức | R79: Sanotec DREAM control | S79: 370000000 | U79: 370000000 | V79: 378000000 | X79: 25000000 | Y79: 6000000 | Z79: 45492 | AA79: D200672024
A80: 45556 | B80: 1205/HĐ-2024 | C80: 77/7 đường phan đình phùng, p. quang vinh, biên hòa, đồng nai | D80: Đồng Nai | E80: =VLOOKUP(D80,'shipping inf'!B:D,2,FALSE) -> Đồng Nai | F80: KH074 | G80: 90 | H80: 2411200501 | I80: D2006 | J80: 24 | K80: 24 | L80: Sales MQH cá nhân | M80: Sanyo Minh Long | N80: =VLOOKUP(Table1[[#This Row],[elevator_traction_machine]],'Product inf'!A:B,2,FALSE) -> SP006 | O80: Kết cấu thép | P80: Tải khách | Q80: Sanotec - Nhật Bản | R80: Sanotec DREAM control | S80: 622000000 | U80: 622000000 | V80: 629023000 | X80: 20000000 | Y80: 8000000 | Z80: 45559 | AA80: D200692024
A81: 45745 | B81: 1205/HĐ-2025 | C81: 64-2 cù lao, phường 2, quận phú nhuận, tphcm | D81: TP Hồ Chí Minh | E81: =VLOOKUP(D81,'shipping inf'!B:D,2,FALSE) -> TP Hồ Chí Minh | F81: KH075 | G81: 120 | H81: 2511200501 | I81: D2006 | J81: 24 | K81: 36 | L81: Sales MQH cá nhân | M81: Sanyo Minh Long | N81: =VLOOKUP(Table1[[#This Row],[elevator_traction_machine]],'Product inf'!A:B,2,FALSE) -> SP015 | O81: Bê tông | P81: Tải khách | Q81: Ziehl-Abegg - Đức | R81: Sanotec DREAM control | S81: 385000000 | U81: 385000000 | V81: 396000000 | X81: 35000000 | Y81: 6000000 | Z81: 45747 | AA81: D200632025
A82: 45548 | B82: 1206/HĐ-2024 | C82: 38 đường số 2, kp2, p. bình chiểu, tp. thủ đức, tp. hcm | D82: TP Hồ Chí Minh | E82: =VLOOKUP(D82,'shipping inf'!B:D,2,FALSE) -> TP Hồ Chí Minh | F82: KH076 | G82: 120 | H82: 2411200601 | I82: D2006 | J82: 24 | K82: 24 | L82: MKT Đối tác | M82: Sanyo Minh Long | N82: =VLOOKUP(Table1[[#This Row],[elevator_traction_machine]],'Product inf'!A:B,2,FALSE) -> SP015 | O82: Kết cấu thép | P82: Tải khách | Q82: Ziehl-Abegg - Đức | R82: Sanotec DREAM control | S82: 550000000 | U82: 550000000 | V82: 549650000 | X82: 23000000 | Y82: 6000000 | Z82: 45552 | AA82: D200692024
A83: 45768 | B83: 1206/HĐ-2025 | C83: lk7-47, p. bình trưng tây, tp thủ đức, tphcm | D83: TP Hồ Chí Minh | E83: =VLOOKUP(D83,'shipping inf'!B:D,2,FALSE) -> TP Hồ Chí Minh | F83: KH077 | G83: 120 | H83: 2511200601 | I83: D2006 | J83: 24 | K83: 24 | L83: Sales MQH cá nhân | M83: Sanyo Minh Long | N83: =VLOOKUP(Table1[[#This Row],[elevator_traction_machine]],'Product inf'!A:B,2,FALSE) -> SP015 | O83: Bê tông | P83: Tải khách | Q83: Ziehl-Abegg - Đức | R83: Sanotec DREAM control | S83: 570000000 | T83: 45600000 | U83: 615600000 | V83: 569600000 | X83: 30000000 | Y83: 10000000 | Z83: 45768 | AA83: D200642025
A84: 45575 | B84: 1207/HĐ-2024 | C84: b2-11-05 phú gia, đường 38-cl, p. cát lái, tp. thủ đức, tp. hcm | D84: TP Hồ Chí Minh | E84: =VLOOKUP(D84,'shipping inf'!B:D,2,FALSE) -> TP Hồ Chí Minh | F84: KH078 | G84: 120 | H84: 2411200701 | I84: D2006 | J84: 24 | K84: 24 | L84: Sales MQH cá nhân | M84: Sanyo Minh Long | N84: =VLOOKUP(Table1[[#This Row],[elevator_traction_machine]],'Product inf'!A:B,2,FALSE) -> SP006 | O84: Kết cấu thép | P84: Tải khách | Q84: Sanotec - Nhật Bản | R84: Sanotec DREAM control | S84: 390000000 | U84: 390000000 | V84: 379340000 | X84: 20000000 | Y84: 6000000 | Z84: 45577 | AA84: D2006102024
A85: 45783 | B85: 1207/HĐ-2025 | C85: 8/19b hẻm 2, đường huỳnh tấn phát, kp. hiệp lễ, p. hiệp ninh, tp. tây ninh | D85: Tây Ninh | E85: =VLOOKUP(D85,'shipping inf'!B:D,2,FALSE) -> Tây Ninh | F85: KH079 | G85: 120 | H85: 2511200701 | I85: D2006 | J85: 24 | K85: 24 | L85: Sales MQH cá nhân | M85: Sanyo Minh Long | N85: =VLOOKUP(Table1[[#This Row],[elevator_traction_machine]],'Product inf'!A:B,2,FALSE) -> SP006 | O85: Bê tông | P85: Tải khách | Q85: Sanotec - Nhật Bản | R85: Sanotec DREAM control | S85: 380000000 | U85: 380000000 | V85: 380500000 | X85: 40000000 | Y85: 10000000 | Z85: 45783 | AA85: D200652025
A86: 45791 | B86: 1208/HĐ-2025 | C86: 158a võ thị sáu, phường 8, quận 3, tphcm | D86: TP Hồ Chí Minh | E86: =VLOOKUP(D86,'shipping inf'!B:D,2,FALSE) -> TP Hồ Chí Minh | F86: KH080 | G86: 90 | H86: 2511200801 | I86: D2006 | J86: 24 | K86: 24 | L86: MKT Chương trình sự kiện | M86: Sanyo Minh Long | N86: =VLOOKUP(Table1[[#This Row],[elevator_traction_machine]],'Product inf'!A:B,2,FALSE) -> SP006 | O86: Kết cấu thép | P86: Tải khách | Q86: Sanotec - Nhật Bản | R86: Sanotec DREAM control | S86: 1096000000 | T86: 87680000 | U86: 1183680000 | V86: 1093500000 | X86: 30000000 | Y86: 14000000 | Z86: 45800 | AA86: D200652025
A87: 45828 | B87: 1209/HĐ-2025 | C87: 575 nguyễn trãi, phường 07, quận 05, tphcm | D87: TP Hồ Chí Minh | E87: =VLOOKUP(D87,'shipping inf'!B:D,2,FALSE) -> TP Hồ Chí Minh | F87: KH081 | G87: 150 | H87: 2511200901 | I87: D2006 | J87: 24 | K87: 24 | L87: Sales MQH cá nhân | M87: Sanyo Minh Long | N87: =VLOOKUP(Table1[[#This Row],[elevator_traction_machine]],'Product inf'!A:B,2,FALSE) -> SP015 | O87: Bê tông | P87: Tải khách | Q87: Ziehl-Abegg - Đức | R87: Sanotec DREAM control | S87: 425000000 | U87: 425000000 | V87: 448320000 | W87: 25000000 | X87: 20000000 | Y87: 10000000 | Z87: 45828 | AA87: D200662025
A88: 45491 | B88: 121/HĐ-2024 | C88: nhà số 5, khu biệt thự 816, đường nguyễn duy trinh, p. phú hữu, tp. thủ đức, tp. hcm | D88: TP Hồ Chí Minh | E88: =VLOOKUP(D88,'shipping inf'!B:D,2,FALSE) -> TP Hồ Chí Minh | F88: KH017 | G88: 40 | H88: 2410102101 | I88: D3001 | J88: 24 | K88: 12 | L88: Ban Giám Đốc | M88: Sanyo Minh Long | N88: =VLOOKUP(Table1[[#This Row],[elevator_traction_machine]],'Product inf'!A:B,2,FALSE) -> SP009 | O88: Bê tông | P88: Tải khách | Q88: Sanotec Eco - Nhật Bản | R88: Sanotec DREAM control | S88: 390000000 | U88: 390000000 | Y88: 4900000 | Z88: 45492 | AA88: D300172024
A89: 45784 | B89: 121/HĐ-2025 | C89: 02 nguyễn tri phương, phường phú nhuận, quận thuận hóa, thành phố huế pl1 | D89: Huế (Thừa Thiên Huế) | E89: =VLOOKUP(D89,'shipping inf'!B:D,2,FALSE) -> Huế | F89: KH082 | G89: 90 | H89: 2510102101 | I89: D3001 | J89: 12 | K89: 12 | L89: Ban Giám Đốc | M89: Sanyo Minh Long | N89: =VLOOKUP(Table1[[#This Row],[elevator_traction_machine]],'Product inf'!A:B,2,FALSE) -> SP006 | O89: Bê tông | P89: Tải hàng | Q89: Sanotec - Nhật Bản | R89: Sanotec DREAM control | S89: 1976000000 | T89: 158080000 | U89: 2134080000 | V89: 1976000000 | Y89: 40000000 | Z89: 45784 | AA89: D300152025
A90: 45784 | B90: 121/HĐ-2025 | C90: 02 nguyễn tri phương, phường phú nhuận, quận thuận hóa, thành phố huế pl2 | D90: Huế (Thừa Thiên Huế) | E90: =VLOOKUP(D90,'shipping inf'!B:D,2,FALSE) -> Huế | F90: KH082 | G90: 90 | H90: 2510102102 | I90: D3001 | J90: 12 | K90: 12 | L90: Ban Giám Đốc | M90: Sanyo Minh Long | N90: =VLOOKUP(Table1[[#This Row],[elevator_traction_machine]],'Product inf'!A:B,2,FALSE) -> SP006 | O90: Bê tông | P90: Tải hàng | Q90: Sanotec - Nhật Bản | R90: Sanotec DREAM control | U90: 0 | Z90: 45784 | AA90: D300152025
A91: 45784 | B91: 121/HĐ-2025 | C91: 02 nguyễn tri phương, phường phú nhuận, quận thuận hóa, thành phố huế pl3 | D91: Huế (Thừa Thiên Huế) | E91: =VLOOKUP(D91,'shipping inf'!B:D,2,FALSE) -> Huế | F91: KH082 | G91: 90 | H91: 2510102103 | I91: D3001 | J91: 12 | K91: 12 | L91: Ban Giám Đốc | M91: Sanyo Minh Long | N91: =VLOOKUP(Table1[[#This Row],[elevator_traction_machine]],'Product inf'!A:B,2,FALSE) -> SP006 | O91: Bê tông | P91: Tải khách + hàng | Q91: Sanotec - Nhật Bản | R91: Sanotec DREAM control | U91: 0 | Z91: 45784 | AA91: D300152025
A92: 45869 | B92: 1210/HĐ-2025 | C92: khu đất thuộc ô 20, lô bt-01, kdc bình trưng tây, quận 2, tphcm | D92: TP Hồ Chí Minh | E92: =VLOOKUP(D92,'shipping inf'!B:D,2,FALSE) -> TP Hồ Chí Minh | F92: KH077 | G92: 150 | H92: 2511201001 | I92: D2006 | J92: 24 | K92: 24 | L92: Sales MQH cá nhân | M92: Sanyo Minh Long | N92: =VLOOKUP(Table1[[#This Row],[elevator_traction_machine]],'Product inf'!A:B,2,FALSE) -> SP015 | O92: Kết cấu thép | P92: Tải khách | Q92: Ziehl-Abegg - Đức | R92: Sanotec CEN control | S92: 657000000 | T92: 52560000 | U92: 709560000 | V92: 661595060 | X92: 10000000 | Y92: 12000000 | Z92: 45876 | AA92: D200672025
A93: 45938 | B93: 1211/HĐ-2025 | C93: 16 đường số 3, kdc khang an, quận 9, tphcm | D93: TP Hồ Chí Minh | E93: =VLOOKUP(D93,'shipping inf'!B:D,2,FALSE) -> TP Hồ Chí Minh | F93: KH083 | G93: 120 | H93: 2511201101 | I93: D2006 | J93: 24 | K93: 24 | L93: Sales MQH cá nhân | M93: Sanyo Minh Long | N93: =VLOOKUP(Table1[[#This Row],[elevator_traction_machine]],'Product inf'!A:B,2,FALSE) -> SP006 | O93: Bê tông | P93: Tải khách | Q93: Sanotec - Nhật Bản | R93: Sanotec DREAM control | S93: 367000000 | U93: 367000000 | V93: 374000000 | X93: 10000000 | Y93: 6000000 | Z93: 45939 | AA93: D2006102025
A94: 45965 | B94: 1212/HĐ-2025 | C94: 1181,14,16 lê văn lương, phước kiển, nhà bè, tphcm | D94: TP Hồ Chí Minh | E94: =VLOOKUP(D94,'shipping inf'!B:D,2,FALSE) -> TP Hồ Chí Minh | F94: KH084 | G94: 150 | H94: 2511201201 | I94: D2006 | J94: 24 | K94: 24 | L94: Sales MQH cá nhân | M94: Sanyo Minh Long | N94: =VLOOKUP(Table1[[#This Row],[elevator_traction_machine]],'Product inf'!A:B,2,FALSE) -> SP006 | O94: Bê tông | P94: Tải khách | Q94: Sanotec - Nhật Bản | R94: Sanotec DREAM control | S94: 354500000 | U94: 354500000 | V94: 370000000 | X94: 5000000 | Y94: 10000000 | Z94: 45966 | AA94: D2006112025
A95: 45930 | B95: 1214/HĐ-2025 | C95: 61b nguyễn văn đậu, p.5, q.bình thạnh, tphcm | D95: TP Hồ Chí Minh | E95: =VLOOKUP(D95,'shipping inf'!B:D,2,FALSE) -> TP Hồ Chí Minh | F95: KH085 | G95: 90 | H95: 2511201401 | I95: D2006 | J95: 24 | K95: 24 | L95: Sales MQH cá nhân | M95: Sanyo Minh Long | N95: =VLOOKUP(Table1[[#This Row],[elevator_traction_machine]],'Product inf'!A:B,2,FALSE) -> SP006 | O95: Bê tông | P95: Tải khách | Q95: Sanotec - Nhật Bản | R95: Sanotec DREAM control | S95: 508000000 | T95: 40640000 | U95: 548640000 | V95: 398000000 | X95: 10000000 | Y95: 10000000 | Z95: 45941 | AA95: D200692025
A96: 45965 | B96: 1215/HĐ-2025 | C96: lô j35, kdc himlam, p.tân hưng, q.7, tphcm | D96: TP Hồ Chí Minh | E96: =VLOOKUP(D96,'shipping inf'!B:D,2,FALSE) -> TP Hồ Chí Minh | F96: KH086 | G96: 120 | H96: 2511201501 | I96: D2006 | J96: 24 | K96: 24 | L96: Sales MQH cá nhân | M96: Sanyo Minh Long | N96: =VLOOKUP(Table1[[#This Row],[elevator_traction_machine]],'Product inf'!A:B,2,FALSE) -> SP006 | O96: Bê tông | P96: Tải khách | Q96: Sanotec - Nhật Bản | R96: Sanotec DREAM control | S96: 385500000 | U96: 385500000 | V96: 386000000 | X96: 20000000 | Y96: 10000000 | Z96: 45966 | AA96: D2006112025
A97: 45937 | B97: 1216/HĐ-2025 | C97: c26, dự án kđt mới tây sông hậu, long xuyên, an giang | D97: An Giang | E97: =VLOOKUP(D97,'shipping inf'!B:D,2,FALSE) -> An Giang | F97: KH087 | G97: 60 | H97: 2511201601 | I97: D2006 | J97: 24 | K97: 24 | L97: Sales MQH cá nhân | M97: Sanyo Minh Long | N97: =VLOOKUP(Table1[[#This Row],[elevator_traction_machine]],'Product inf'!A:B,2,FALSE) -> SP006 | O97: Bê tông | P97: Tải khách | Q97: Sanotec - Nhật Bản | R97: Sanotec DREAM control | S97: 360000000 | U97: 360000000 | V97: 375000000 | X97: 20000000 | Y97: 6000000 | Z97: 45937 | AA97: D2006102025
A98: 45947 | B98: 1217/HĐ-2025 | C98: 4/1 bàu bàng, phường tân bình, tp.hcm | D98: TP Hồ Chí Minh | E98: =VLOOKUP(D98,'shipping inf'!B:D,2,FALSE) -> TP Hồ Chí Minh | F98: KH088 | G98: 90 | H98: 2511201701 | I98: D2006 | J98: 24 | K98: 36 | L98: Sales MQH cá nhân | M98: Sanyo Minh Long | N98: =VLOOKUP(Table1[[#This Row],[elevator_traction_machine]],'Product inf'!A:B,2,FALSE) -> SP006 | O98: Bê tông | P98: Tải khách | Q98: Sanotec - Nhật Bản | R98: Sanotec DREAM control | S98: 385000000 | U98: 385000000 | V98: 385000000 | X98: 10000000 | Y98: 10000000 | Z98: 45947 | AA98: D2006102025
A99: 46014 | B99: 1219/HĐ-2025 | C99: số 10 đường 37, p.bình trưng, tphcm | D99: TP Hồ Chí Minh | E99: =VLOOKUP(D99,'shipping inf'!B:D,2,FALSE) -> TP Hồ Chí Minh | F99: KH089 | G99: 120 | H99: 2511201901 | I99: D2006 | J99: 24 | K99: 24 | L99: Sales MQH cá nhân | M99: Sanyo Minh Long | N99: =VLOOKUP(Table1[[#This Row],[elevator_traction_machine]],'Product inf'!A:B,2,FALSE) -> SP015 | O99: Bê tông | P99: Tải khách | Q99: Ziehl-Abegg - Đức | R99: Sanotec DREAM control | S99: 407000000 | U99: 407000000 | V99: 407300000 | X99: 15000000 | Y99: 10000000 | Z99: 46014 | AA99: D2006122025
A100: 45479 | B100: 122/HĐ-2024 | C100: 457/19 hòa hảo, p.5, q.10, tp. hcm | D100: TP Hồ Chí Minh | E100: =VLOOKUP(D100,'shipping inf'!B:D,2,FALSE) -> TP Hồ Chí Minh | F100: KH090 | G100: 90 | H100: 2410102201 | I100: D3001 | J100: 24 | K100: 12 | L100: Ban Giám Đốc | M100: Sanyo Minh Long | N100: =VLOOKUP(Table1[[#This Row],[elevator_traction_machine]],'Product inf'!A:B,2,FALSE) -> SP006 | O100: Bê tông | P100: Tải khách | Q100: Sanotec - Nhật Bản | R100: Sanotec DREAM control | S100: 360000000 | U100: 360000000 | X100: 15000000 | Y100: 4600000 | Z100: 45483 | AA100: D300172024
...

Sheet Appendix data
A1: Appendix_date | B1: appendix_sequence | C1: contract_ID | D1: customer_ID | E1: appendix_value_before_tax | F1: appendix_vat_amountuế GTGT | G1: appendix_value_after_tax | H1: appendix_type
A2: 45664 | B2: 1 | C2: 207/HĐ-2024 | D2: =VLOOKUP(Table2[[#This Row],[contract_ID]],'Contract data'!B:F,5,FALSE) -> KH208 | E2: 6000000 | G2: 6000000 | H2: Variation Appendix
A3: 45665 | B3: 1 | C3: 401/HĐ-2024 | D3: =VLOOKUP(Table2[[#This Row],[contract_ID]],'Contract data'!B:F,5,FALSE) -> KH254 | G3: 0 | H3: No-Cost Addendum
A4: 45670 | B4: 1 | C4: 1001/HĐ-2024 | D4: =VLOOKUP(Table2[[#This Row],[contract_ID]],'Contract data'!B:F,5,FALSE) -> KH001 | G4: 0 | H4: No-Cost Addendum
A5: 45669 | B5: 1 | C5: 1110/HĐ-2024 | D5: =VLOOKUP(Table2[[#This Row],[contract_ID]],'Contract data'!B:F,5,FALSE) -> KH045 | G5: 0 | H5: No-Cost Addendum
A6: 45670 | B6: 1 | C6: 1105/HĐ-2024 | D6: =VLOOKUP(Table2[[#This Row],[contract_ID]],'Contract data'!B:F,5,FALSE) -> KH037 | E6: -2000000 | G6: -2000000 | H6: Deduction Appendix
A7: 45661 | B7: 1 | C7: 1112/HĐ-2024 | D7: =VLOOKUP(Table2[[#This Row],[contract_ID]],'Contract data'!B:F,5,FALSE) -> KH047 | E7: -2000000 | G7: -2000000 | H7: Deduction Appendix
A8: 45673 | B8: 1 | C8: 517/HĐ-2024 | D8: =VLOOKUP(Table2[[#This Row],[contract_ID]],'Contract data'!B:F,5,FALSE) -> KH284 | G8: 0 | H8: No-Cost Addendum
A9: 45673 | B9: 1 | C9: 504/HĐ-2024 | D9: =VLOOKUP(Table2[[#This Row],[contract_ID]],'Contract data'!B:F,5,FALSE) -> KH268 | G9: 0 | H9: No-Cost Addendum
A10: 45677 | B10: 1 | C10: 613/HĐ-2024 | D10: =VLOOKUP(Table2[[#This Row],[contract_ID]],'Contract data'!B:F,5,FALSE) -> KH310 | E10: 2500000 | G10: 2500000 | H10: Variation Appendix
A11: 45677 | B11: 1 | C11: 125/HĐ-2024 | D11: =VLOOKUP(Table2[[#This Row],[contract_ID]],'Contract data'!B:F,5,FALSE) -> KH095 | E11: -1600000 | G11: -1600000 | H11: Deduction Appendix
A12: 45671 | B12: 1 | C12: 126/HĐ-2024 | D12: =VLOOKUP(Table2[[#This Row],[contract_ID]],'Contract data'!B:F,5,FALSE) -> KH097 | E12: 41000000 | G12: 41000000 | H12: Variation Appendix
A13: 45680 | B13: 1 | C13: 115/HĐ-2024 | D13: =VLOOKUP(Table2[[#This Row],[contract_ID]],'Contract data'!B:F,5,FALSE) -> KH056 | G13: 0 | H13: No-Cost Addendum
A14: 45694 | B14: 1 | C14: 134/HĐ-2024 | D14: =VLOOKUP(Table2[[#This Row],[contract_ID]],'Contract data'!B:F,5,FALSE) -> KH110 | G14: 0 | H14: No-Cost Addendum
A15: 45679 | B15: 1 | C15: 1202/HĐ-2024 | D15: =VLOOKUP(Table2[[#This Row],[contract_ID]],'Contract data'!B:F,5,FALSE) -> KH070 | E15: 3000000 | G15: 3000000 | H15: Variation Appendix
A16: 45688 | B16: 1 | C16: 601/HĐ-2025 | D16: =VLOOKUP(Table2[[#This Row],[contract_ID]],'Contract data'!B:F,5,FALSE) -> KH290 | G16: 0 | H16: No-Cost Addendum
A17: 45698 | B17: 1 | C17: 213/HĐ-2024 | D17: =VLOOKUP(Table2[[#This Row],[contract_ID]],'Contract data'!B:F,5,FALSE) -> KH219 | G17: 0 | H17: No-Cost Addendum
A18: 45698 | B18: 2 | C18: 134/HĐ-2024 | D18: =VLOOKUP(Table2[[#This Row],[contract_ID]],'Contract data'!B:F,5,FALSE) -> KH110 | G18: 0 | H18: No-Cost Addendum
A19: 45701 | B19: 1 | C19: 520/HĐ-2024 | D19: =VLOOKUP(Table2[[#This Row],[contract_ID]],'Contract data'!B:F,5,FALSE) -> KH287 | G19: 0 | H19: No-Cost Addendum
A20: 45698 | B20: 1 | C20: 141/HĐ-2024 | D20: =VLOOKUP(Table2[[#This Row],[contract_ID]],'Contract data'!B:F,5,FALSE) -> KH121 | E20: 40000000 | G20: 40000000 | H20: Variation Appendix
A21: 45703 | B21: 1 | C21: 1206/HĐ-2024 | D21: =VLOOKUP(Table2[[#This Row],[contract_ID]],'Contract data'!B:F,5,FALSE) -> KH076 | G21: 0 | H21: No-Cost Addendum
A22: 45705 | B22: 1 | C22: 814/HĐ-2024 | D22: =VLOOKUP(Table2[[#This Row],[contract_ID]],'Contract data'!B:F,5,FALSE) -> KH354 | E22: 12000000 | G22: 12000000 | H22: Variation Appendix
A23: 45706 | B23: 1 | C23: 819/HĐ-2024 | D23: =VLOOKUP(Table2[[#This Row],[contract_ID]],'Contract data'!B:F,5,FALSE) -> KH364 | G23: 0 | H23: No-Cost Addendum
A24: 45713 | B24: 3 | C24: 134/HĐ-2024 | D24: =VLOOKUP(Table2[[#This Row],[contract_ID]],'Contract data'!B:F,5,FALSE) -> KH110 | E24: 25500000 | G24: 25500000 | H24: Variation Appendix
A25: 45714 | B25: 1 | C25: 139/HĐ-2024 | D25: =VLOOKUP(Table2[[#This Row],[contract_ID]],'Contract data'!B:F,5,FALSE) -> KH011 | G25: 0 | H25: No-Cost Addendum
A26: 45714 | B26: 1 | C26: 140/HĐ-2024 | D26: =VLOOKUP(Table2[[#This Row],[contract_ID]],'Contract data'!B:F,5,FALSE) -> KH119 | G26: 0 | H26: No-Cost Addendum
A27: 45715 | B27: 2 | C27: 1202/HĐ-2024 | D27: =VLOOKUP(Table2[[#This Row],[contract_ID]],'Contract data'!B:F,5,FALSE) -> KH070 | E27: 20600000 | G27: 20600000 | H27: Variation Appendix
A28: 45719 | B28: 2 | C28: 141/HĐ-2024 | D28: =VLOOKUP(Table2[[#This Row],[contract_ID]],'Contract data'!B:F,5,FALSE) -> KH121 | E28: 38500000 | G28: 38500000 | H28: Variation Appendix
A29: 45715 | B29: 1 | C29: 1201/HĐ-2025 | D29: =VLOOKUP(Table2[[#This Row],[contract_ID]],'Contract data'!B:F,5,FALSE) -> KH068 | G29: 0 | H29: No-Cost Addendum
A30: 45715 | B30: 1 | C30: 135/HĐ-2024 | D30: =VLOOKUP(Table2[[#This Row],[contract_ID]],'Contract data'!B:F,5,FALSE) -> KH112 | E30: 35500000 | G30: 35500000 | H30: Variation Appendix
A31: 45714 | B31: 1 | C31: 309/HĐ-2024 | D31: =VLOOKUP(Table2[[#This Row],[contract_ID]],'Contract data'!B:F,5,FALSE) -> KH240 | E31: 61500000 | G31: 61500000 | H31: Variation Appendix
A32: 45715 | B32: 2 | C32: 309/HĐ-2024 | D32: =VLOOKUP(Table2[[#This Row],[contract_ID]],'Contract data'!B:F,5,FALSE) -> KH240 | G32: 0 | H32: No-Cost Addendum
A33: 45724 | B33: 2 | C33: 1206/HĐ-2024 | D33: =VLOOKUP(Table2[[#This Row],[contract_ID]],'Contract data'!B:F,5,FALSE) -> KH076 | E33: 800000 | G33: 800000 | H33: Variation Appendix
A34: 45721 | B34: 4 | C34: 134/HĐ-2024 | D34: =VLOOKUP(Table2[[#This Row],[contract_ID]],'Contract data'!B:F,5,FALSE) -> KH110 | G34: 0 | H34: No-Cost Addendum
A35: 45708 | B35: 1 | C35: 122/HĐ-2024 | D35: =VLOOKUP(Table2[[#This Row],[contract_ID]],'Contract data'!B:F,5,FALSE) -> KH090 | E35: 33000000 | G35: 33000000 | H35: Variation Appendix
A36: 45726 | B36: 1 | C36: 1504/HĐ-2025 | D36: =VLOOKUP(Table2[[#This Row],[contract_ID]],'Contract data'!B:F,5,FALSE) -> KH140 | E36: -1200000 | G36: -1200000 | H36: Deduction Appendix
A37: 45715 | B37: 3 | C37: 1202/HĐ-2024 | D37: =VLOOKUP(Table2[[#This Row],[contract_ID]],'Contract data'!B:F,5,FALSE) -> KH070 | G37: 0 | H37: No-Cost Addendum
A38: 45728 | B38: 1 | C38: 302/HĐ-2025 | D38: =VLOOKUP(Table2[[#This Row],[contract_ID]],'Contract data'!B:F,5,FALSE) -> KH230 | G38: 0 | H38: No-Cost Addendum
A39: 45730 | B39: 1 | C39: 204/HĐ-2024 | D39: =VLOOKUP(Table2[[#This Row],[contract_ID]],'Contract data'!B:F,5,FALSE) -> KH202 | E39: 10000000 | G39: 10000000 | H39: Variation Appendix
A40: 45734 | B40: 4 | C40: 1202/HĐ-2024 | D40: =VLOOKUP(Table2[[#This Row],[contract_ID]],'Contract data'!B:F,5,FALSE) -> KH070 | E40: 6000000 | G40: 6000000 | H40: Variation Appendix
A41: 45733 | B41: 1 | C41: 104/HĐ-2024 | D41: =VLOOKUP(Table2[[#This Row],[contract_ID]],'Contract data'!B:F,5,FALSE) -> KH009 | E41: 4000000 | G41: 4000000 | H41: Variation Appendix
A42: 45737 | B42: 1 | C42: 604/HĐ-2025 | D42: =VLOOKUP(Table2[[#This Row],[contract_ID]],'Contract data'!B:F,5,FALSE) -> KH295 | G42: 0 | H42: No-Cost Addendum
A43: 45734 | B43: 1 | C43: 106/HĐ-2025 | D43: =VLOOKUP(Table2[[#This Row],[contract_ID]],'Contract data'!B:F,5,FALSE) -> KH015 | G43: 0 | H43: No-Cost Addendum
A44: 45747 | B44: 2 | C44: 1201/HĐ-2025 | D44: =VLOOKUP(Table2[[#This Row],[contract_ID]],'Contract data'!B:F,5,FALSE) -> KH068 | E44: 6500000 | G44: 6500000 | H44: Variation Appendix
A45: 45747 | B45: 1 | C45: 1601/HĐ-2025 | D45: =VLOOKUP(Table2[[#This Row],[contract_ID]],'Contract data'!B:F,5,FALSE) -> KH165 | E45: 25720000 | G45: 25720000 | H45: Variation Appendix
A46: 45758 | B46: 2 | C46: 106/HĐ-2025 | D46: =VLOOKUP(Table2[[#This Row],[contract_ID]],'Contract data'!B:F,5,FALSE) -> KH015 | G46: 0 | H46: No-Cost Addendum
A47: 45731 | B47: 1 | C47: 1101/HĐ-2025 | D47: =VLOOKUP(Table2[[#This Row],[contract_ID]],'Contract data'!B:F,5,FALSE) -> KH030 | G47: 0 | H47: No-Cost Addendum
A48: 45764 | B48: 2 | C48: 1001/HĐ-2024 | D48: =VLOOKUP(Table2[[#This Row],[contract_ID]],'Contract data'!B:F,5,FALSE) -> KH001 | G48: 0 | H48: No-Cost Addendum
A49: 45768 | B49: 1 | C49: 615/HĐ-2024 | D49: =VLOOKUP(Table2[[#This Row],[contract_ID]],'Contract data'!B:F,5,FALSE) -> KH314 | E49: -2565000 | G49: -2565000 | H49: Deduction Appendix
A50: 45768 | B50: 1 | C50: 605/HĐ-2025 | D50: =VLOOKUP(Table2[[#This Row],[contract_ID]],'Contract data'!B:F,5,FALSE) -> KH297 | E50: 10000000 | G50: 10000000 | H50: Variation Appendix
A51: 45771 | B51: 1 | C51: 402/HĐ-2024 | D51: =VLOOKUP(Table2[[#This Row],[contract_ID]],'Contract data'!B:F,5,FALSE) -> KH257 | E51: -24500000 | G51: -24500000 | H51: Deduction Appendix
A52: 45771 | B52: 1 | C52: 901/HĐ-2025 | D52: =VLOOKUP(Table2[[#This Row],[contract_ID]],'Contract data'!B:F,5,FALSE) -> KH368 | G52: 0 | H52: No-Cost Addendum
A53: 45771 | B53: 1 | C53: 1505/HĐ-2025 | D53: =VLOOKUP(Table2[[#This Row],[contract_ID]],'Contract data'!B:F,5,FALSE) -> KH142 | E53: 10000000 | G53: 10000000 | H53: Variation Appendix
A54: 45769 | B54: 1 | C54: 1108/HĐ-2024 | D54: =VLOOKUP(Table2[[#This Row],[contract_ID]],'Contract data'!B:F,5,FALSE) -> KH041 | E54: -4500000 | G54: -4500000 | H54: Deduction Appendix
A55: 45782 | B55: 1 | C55: 506/HĐ-2025 | D55: =VLOOKUP(Table2[[#This Row],[contract_ID]],'Contract data'!B:F,5,FALSE) -> KH157 | G55: 0 | H55: No-Cost Addendum
A56: 45784 | B56: 1 | C56: 1106/HĐ-2024 | D56: =VLOOKUP(Table2[[#This Row],[contract_ID]],'Contract data'!B:F,5,FALSE) -> KH039 | G56: 0 | H56: No-Cost Addendum
A57: 45784 | B57: 1 | C57: 1104/HĐ-2025 | D57: =VLOOKUP(Table2[[#This Row],[contract_ID]],'Contract data'!B:F,5,FALSE) -> KH036 | G57: 0 | H57: No-Cost Addendum
A58: 45789 | B58: 3 | C58: 141/HĐ-2024 | D58: =VLOOKUP(Table2[[#This Row],[contract_ID]],'Contract data'!B:F,5,FALSE) -> KH121 | E58: 900000 | G58: 900000 | H58: Variation Appendix
A59: 45790 | B59: 1 | C59: 216/HĐ-2024 | D59: =VLOOKUP(Table2[[#This Row],[contract_ID]],'Contract data'!B:F,5,FALSE) -> KH224 | E59: 18000000 | G59: 18000000 | H59: Variation Appendix
A60: 45790 | B60: 1 | C60: 121/HĐ-2025 | D60: =VLOOKUP(Table2[[#This Row],[contract_ID]],'Contract data'!B:F,5,FALSE) -> KH082 | G60: 0 | H60: No-Cost Addendum
A61: 45794 | B61: 1 | C61: 112/HĐ-2025 | D61: =VLOOKUP(Table2[[#This Row],[contract_ID]],'Contract data'!B:F,5,FALSE) -> KH053 | G61: 0 | H61: No-Cost Addendum
A62: 45794 | B62: 1 | C62: 107/HĐ-2025 | D62: =VLOOKUP(Table2[[#This Row],[contract_ID]],'Contract data'!B:F,5,FALSE) -> KH018 | G62: 0 | H62: No-Cost Addendum
A63: 45791 | B63: 1 | C63: 105/HĐ-2025 | D63: =VLOOKUP(Table2[[#This Row],[contract_ID]],'Contract data'!B:F,5,FALSE) -> KH012 | G63: 0 | H63: No-Cost Addendum
A64: 45800 | B64: 2 | C64: 402/HĐ-2024 | D64: =VLOOKUP(Table2[[#This Row],[contract_ID]],'Contract data'!B:F,5,FALSE) -> KH257 | G64: 0 | H64: No-Cost Addendum
A65: 45804 | B65: 3 | C65: 402/HĐ-2024 | D65: =VLOOKUP(Table2[[#This Row],[contract_ID]],'Contract data'!B:F,5,FALSE) -> KH257 | G65: 0 | H65: No-Cost Addendum
A66: 45805 | B66: 1 | C66: 118/HĐ-2025 | D66: =VLOOKUP(Table2[[#This Row],[contract_ID]],'Contract data'!B:F,5,FALSE) -> KH062 | G66: 0 | H66: No-Cost Addendum
A67: 45800 | B67: 2 | C67: 107/HĐ-2025 | D67: =VLOOKUP(Table2[[#This Row],[contract_ID]],'Contract data'!B:F,5,FALSE) -> KH018 | E67: -2500000 | G67: -2500000 | H67: Deduction Appendix
A68: 45811 | B68: 1 | C68: 503/HĐ-2025 | D68: =VLOOKUP(Table2[[#This Row],[contract_ID]],'Contract data'!B:F,5,FALSE) -> KH267 | G68: 0 | H68: No-Cost Addendum
A69: 45804 | B69: 1 | C69: 1114/HĐ-2024 | D69: =VLOOKUP(Table2[[#This Row],[contract_ID]],'Contract data'!B:F,5,FALSE) -> KH048 | G69: 0 | H69: No-Cost Addendum
A70: 45817 | B70: 3 | C70: 309/HĐ-2024 | D70: =VLOOKUP(Table2[[#This Row],[contract_ID]],'Contract data'!B:F,5,FALSE) -> KH240 | E70: -3000000 | G70: -3000000 | H70: Deduction Appendix
A71: 45814 | B71: 1 | C71: 142/HĐ-2024 | D71: =VLOOKUP(Table2[[#This Row],[contract_ID]],'Contract data'!B:F,5,FALSE) -> KH123 | E71: 1200000 | G71: 1200000 | H71: Variation Appendix
A72: 45820 | B72: 1 | C72: 124/HĐ-2025 | D72: =VLOOKUP(Table2[[#This Row],[contract_ID]],'Contract data'!B:F,5,FALSE) -> KH094 | E72: 85000000 | G72: 85000000 | H72: Variation Appendix
A73: 45818 | B73: 1 | C73: 515/HĐ-2024 | D73: =VLOOKUP(Table2[[#This Row],[contract_ID]],'Contract data'!B:F,5,FALSE) -> KH282 | E73: -5000000 | G73: -5000000 | H73: Deduction Appendix
A74: 45804 | B74: 1 | C74: 904/HĐ-2025 | D74: =VLOOKUP(Table2[[#This Row],[contract_ID]],'Contract data'!B:F,5,FALSE) -> KH376 | E74: 15000000 | G74: 15000000 | H74: Variation Appendix
A75: 45800 | B75: 1 | C75: 1205/HĐ-2025 | D75: =VLOOKUP(Table2[[#This Row],[contract_ID]],'Contract data'!B:F,5,FALSE) -> KH075 | E75: 4000000 | G75: 4000000 | H75: Variation Appendix
A76: 45827 | B76: 1 | C76: 114/HĐ-2025 | D76: =VLOOKUP(Table2[[#This Row],[contract_ID]],'Contract data'!B:F,5,FALSE) -> KH055 | G76: 0 | H76: No-Cost Addendum
A77: 45827 | B77: 1 | C77: 132/HĐ-2024 | D77: =VLOOKUP(Table2[[#This Row],[contract_ID]],'Contract data'!B:F,5,FALSE) -> KH107 | E77: -28000000 | G77: -28000000 | H77: Deduction Appendix
A78: 45799 | B78: 1 | C78: 902/HĐ-2025 | D78: =VLOOKUP(Table2[[#This Row],[contract_ID]],'Contract data'!B:F,5,FALSE) -> KH371 | E78: 8000000 | G78: 8000000 | H78: Variation Appendix
A79: 45812 | B79: 2 | C79: 126/HĐ-2024 | D79: =VLOOKUP(Table2[[#This Row],[contract_ID]],'Contract data'!B:F,5,FALSE) -> KH097 | G79: 0 | H79: No-Cost Addendum
A80: 45839 | B80: 1 | C80: 807/HĐ-2024 | D80: =VLOOKUP(Table2[[#This Row],[contract_ID]],'Contract data'!B:F,5,FALSE) -> KH343 | E80: -2000000 | G80: -2000000 | H80: Deduction Appendix
A81: 45798 | B81: 1 | C81: 206/HĐ-2025 | D81: =VLOOKUP(Table2[[#This Row],[contract_ID]],'Contract data'!B:F,5,FALSE) -> KH207 | E81: -100000000 | G81: -100000000 | H81: Deduction Appendix
A82: 45838 | B82: 2 | C82: 216/HĐ-2024 | D82: =VLOOKUP(Table2[[#This Row],[contract_ID]],'Contract data'!B:F,5,FALSE) -> KH224 | E82: 2000000 | G82: 2000000 | H82: Variation Appendix
A83: 45838 | B83: 1 | C83: 1603/HĐ-2025 | D83: =VLOOKUP(Table2[[#This Row],[contract_ID]],'Contract data'!B:F,5,FALSE) -> KH169 | E83: 7750000 | G83: 7750000 | H83: Variation Appendix
A84: 45843 | B84: 2 | C84: 114/HĐ-2025 | D84: =VLOOKUP(Table2[[#This Row],[contract_ID]],'Contract data'!B:F,5,FALSE) -> KH055 | E84: 8000000 | G84: 8000000 | H84: Variation Appendix
A85: 45800 | B85: 1 | C85: 1207/HĐ-2025 | D85: =VLOOKUP(Table2[[#This Row],[contract_ID]],'Contract data'!B:F,5,FALSE) -> KH079 | G85: 0 | H85: No-Cost Addendum
A86: 45840 | B86: 1 | C86: 117/HĐ-2024 | D86: =VLOOKUP(Table2[[#This Row],[contract_ID]],'Contract data'!B:F,5,FALSE) -> KH060 | E86: 1700000000 | G86: 1700000000 | H86: Variation Appendix
A87: 45853 | B87: 1 | C87: 210/HĐ-2025 | D87: =VLOOKUP(Table2[[#This Row],[contract_ID]],'Contract data'!B:F,5,FALSE) -> KH215 | G87: 0 | H87: No-Cost Addendum
A88: 45854 | B88: 1 | C88: 1902/HĐ-2025 | D88: =VLOOKUP(Table2[[#This Row],[contract_ID]],'Contract data'!B:F,5,FALSE) -> KH182 | G88: 0 | H88: No-Cost Addendum
A89: 45853 | B89: 1 | C89: 305/HĐ-2024 | D89: =VLOOKUP(Table2[[#This Row],[contract_ID]],'Contract data'!B:F,5,FALSE) -> KH233 | G89: 0 | H89: No-Cost Addendum
A90: 45854 | B90: 1 | C90: 1508/HĐ-2025 | D90: =VLOOKUP(Table2[[#This Row],[contract_ID]],'Contract data'!B:F,5,FALSE) -> KH148 | G90: 0 | H90: No-Cost Addendum
A91: 45850 | B91: 1 | C91: 614/HĐ-2025 | D91: =VLOOKUP(Table2[[#This Row],[contract_ID]],'Contract data'!B:F,5,FALSE) -> KH313 | E91: 77000000 | G91: 77000000 | H91: Variation Appendix
A92: 45855 | B92: 1 | C92: 115/HĐ-2025 | D92: =VLOOKUP(Table2[[#This Row],[contract_ID]],'Contract data'!B:F,5,FALSE) -> KH057 | E92: -2520000 | G92: -2520000 | H92: Deduction Appendix
A93: 45855 | B93: 1 | C93: 807/HĐ-2025 | D93: =VLOOKUP(Table2[[#This Row],[contract_ID]],'Contract data'!B:F,5,FALSE) -> KH344 | E93: 13000000 | G93: 13000000 | H93: Variation Appendix
A94: 45857 | B94: 2 | C94: 1504/HĐ-2025 | D94: =VLOOKUP(Table2[[#This Row],[contract_ID]],'Contract data'!B:F,5,FALSE) -> KH140 | E94: 10000000 | G94: 10000000 | H94: Variation Appendix
A95: 45859 | B95: 2 | C95: 132/HĐ-2024 | D95: =VLOOKUP(Table2[[#This Row],[contract_ID]],'Contract data'!B:F,5,FALSE) -> KH107 | E95: 54000000 | G95: 54000000 | H95: Variation Appendix
A96: 45859 | B96: 2 | C96: 124/HĐ-2025 | D96: =VLOOKUP(Table2[[#This Row],[contract_ID]],'Contract data'!B:F,5,FALSE) -> KH094 | G96: 0 | H96: No-Cost Addendum
A97: 45838 | B97: 1 | C97: 905/HĐ-2025 | D97: =VLOOKUP(Table2[[#This Row],[contract_ID]],'Contract data'!B:F,5,FALSE) -> KH379 | E97: -1300000 | G97: -1300000 | H97: Deduction Appendix
A98: 45861 | B98: 1 | C98: 907/HĐ-2025 | D98: =VLOOKUP(Table2[[#This Row],[contract_ID]],'Contract data'!B:F,5,FALSE) -> KH383 | E98: 30000000 | G98: 30000000 | H98: Variation Appendix
A99: 45863 | B99: 1 | C99: 701/HĐ-2025 | D99: =VLOOKUP(Table2[[#This Row],[contract_ID]],'Contract data'!B:F,5,FALSE) -> KH324 | E99: 10000000 | G99: 10000000 | H99: Variation Appendix
A100: 45866 | B100: 3 | C100: 216/HĐ-2024 | D100: =VLOOKUP(Table2[[#This Row],[contract_ID]],'Contract data'!B:F,5,FALSE) -> KH224 | G100: 0 | H100: No-Cost Addendum
...

Sheet Customer
A1: customer_name | B1: customer_ID | C1: customer_type | D1: customer_phone
A2: phạm văn sơn | B2: KH001 | C2: private | D2: 913901630
A3: trần dương phương hùng | B3: KH002 | C3: private | D3: 909092650
A4: ông nguyễn khắc giang | B4: KH003 | C4: private | D4: 938836567
A5: huỳnh thị xuân | B5: KH004 | C5: private | D5: 909206494
A6: công ty cổ phần thực phẩm cát hải | B6: KH005 | C6: company | D6: 836204897
A7: ông nguyễn văn nhẫn | B7: KH006 | C7: private | D7: 913906520
A8: nguyễn thị bích ngọc | B8: KH007 | C8: private
A9: công ty tnhh đầu tư phát triển khách sạn hoàng phát | B9: KH008 | C9: company | D9: 968726091
A10: trần mỹ ngọc | B10: KH009 | C10: private | D10: 907031989
A11: ông dương mạnh trung | B11: KH010 | C11: private | D11: 909769980
A12: trần đức thọ | B12: KH011 | C12: private | D12: 965824456
A13: công ty tnhh thương mại - xây dựng lê thành | B13: KH012 | C13: company | D13: 839803129
A14: trần thị bình | B14: KH013 | C14: private | D14: 918319710
A15: đinh hữu nhân | B15: KH014 | C15: private | D15: 908246467
A16: ông tăng viết hùng | B16: KH015 | C16: private | D16: 949371199
A17: tạ anh tuấn | B17: KH016 | C17: private | D17: 908351120
A18: huỳnh thành chung | B18: KH017 | C18: private | D18: 913880000
A19: bà nguyễn tô vân | B19: KH018 | C19: private | D19: 975446462
A20: công ty cp xd nghĩa trung | B20: KH019 | C20: company
A21: nguyễn thanh sơn | B21: KH020 | C21: private | D21: 936188788
A22: bà biện kim loan | B22: KH021 | C22: private | D22: 939695522
A23: trương anh minh | B23: KH022 | C23: private | D23: 971567028
A24: trần vĩnh phúc | B24: KH023 | C24: private | D24: 932009799
A25: ông vũ bá ổn | B25: KH024 | C25: private | D25: 913235546
A26: công ty tnhh căn hộ mt thảo điền | B26: KH025 | C26: company | D26: 967138868
A27: lê chuyển | B27: KH026 | C27: private | D27: 985923471
A28: ông bùi lê khiêm | B28: KH027 | C28: private | D28: 901125423
A29: đặng minh sơn | B29: KH028 | C29: private | D29: 907298678
A30: trần thái hưng | B30: KH029 | C30: private | D30: 913780859
A31: bà ngô thị lâm | B31: KH030 | C31: private | D31: 913194045
A32: lê nguyễn ngọc vũ | B32: KH031 | C32: private | D32: 904798968
... A44: công ty cổ phần tư vấn thiết kế và đầu tư xây dựng đất việt | B44: KH043 | C44: company | D44: 422111999
A45: công ty tnhh nguồn á châu | B45: KH044 | C45: company
A46: huỳnh minh tuyến | B46: KH045 | C46: private | D46: 908774006
A47: trần quang hiển | B47: KH046 | C47: private | D47: 918603799
A48: nguyễn văn thống | B48: KH047 | C48: private | D48: 988818083
A49: nguyễn hữu trọng | B49: KH048 | C49: private | D49: 966805078
A50: võ tuấn minh | B50: KH049 | C50: private | D50: 987085612
A51: lâm thị mỹ phượng | B51: KH050 | C51: private | D51: 918271527
A52: lê trần thái | B52: KH051 | C52: private | D52: 982255272
A53: đặng đức can cường | B53: KH052 | C53: private
A54: ông nguyễn đình phước | B54: KH053 | C54: private
A55: phạm thị thu thủy | B55: KH054 | C55: private | D55: 382768666
A56: bà tống nguyễn diễm hồng | B56: KH055 | C56: private | D56: 908081348
A57: vũ văn giáp | B57: KH056 | C57: private | D57: 919077146
A58: ông nguyễn minh tân | B58: KH057 | C58: private | D58: 328995148
A59: nguyễn anh tuấn | B59: KH058 | C59: private | D59: 906752999
A60: ông lục chấn bang | B60: KH059 | C60: private | D60: 988922168
A61: công ty cổ phần giấy đồng tiến long an | B61: KH060 | C61: company | D61: 723759992
A62: ông nguyễn thanh hùng | B62: KH061 | C62: private | D62: 903802801
A63: ông lương anh tiến | B63: KH062 | C63: private
A64: công ty cổ phần đầu tư xây dựng viteccons | B64: KH063 | C64: company | D64: 838449123
A65: bà nguyễn hồng phương | B65: KH064 | C65: private | D65: 907277277
A66: phạm thị anh trâm | B66: KH065 | C66: private
A67: phạm thị quỳnh lâm | B67: KH066 | C67: private | D67: 903991999
A68: công ty tnhh dịch vụ thương mại gia mỹ | B68: KH067 | C68: company | D68: 944434815
A69: công ty tnhh maison decor | B69: KH068 | C69: company | D69: 906767509
A70: trần thị hồng nhung | B70: KH069 | C70: private | D70: 909214988
A71: trần văn lý | B71: KH070 | C71: private | D71: 989657236
A72: hồ văn quang | B72: KH071 | C72: private | D72: 918276394
A73: nguyễn gia hào | B73: KH072 | C73: private | D73: 909175549
A74: lê thị phương hiếu | B74: KH073 | C74: private | D74: 908979444
A75: huỳnh thanh châu | B75: KH074 | C75: private | D75: 888881881
A76: bà phan cẩm tú | B76: KH075 | C76: private | D76: 909776747
A77: trương hoàng tâm | B77: KH076 | C77: private | D77: 786312688
A78: công ty tnhh mtv vận tải dòng nước vàng | B78: KH077 | C78: company | D78: 903800494
... A90: nguyễn hữu bình | B90: KH089 | C90: private | D90: 357579497
A91: trương ngọc cúc | B91: KH090 | C91: private
A92: nguyễn thị hương | B92: KH091 | C92: private | D92: 937819686
A93: ông nguyễn văn nam | B93: KH092 | C93: private | D93: 934706372
A94: nguyễn tất lương | B94: KH093 | C94: private | D94: 983346393
A95: ông lê nam hùng | B95: KH094 | C95: private | D95: 906346911
A96: mai thị thu hường | B96: KH095 | C96: private | D96: 988590127
A97: bà nguyễn thị thu nga | B97: KH096 | C97: private | D97: 916249289
A98: vòng thị thúy phượng | B98: KH097 | C98: private | D98: 918158237
A99: nguyễn hoàng việt | B99: KH098 | C99: private | D99: 332051927
A100: công ty tnhh hải sơn | B100: KH099 | C100: company | D100: 917778899
A101: lê công vượng | B101: KH100 | C101: private | D101: 918593236
A102: ông bùi văn trung | B102: KH101 | C102: private | D102: 913894843
A103: trần kiều loan | B103: KH102 | C103: private | D103: 932786878
... A128: thái thanh xuân | B128: KH127 | C128: private | D128: 938683879
A129: nguyễn tấn quang | B129: KH128 | C129: private
A130: hồ thị lan chi | B130: KH129 | C130: private | D130: 918011903
A131: công ty tnhh nha khoa ko.se.i.kai | B131: KH130 | C131: company | D131: 909217661
A132: đỗ thị bích thủy | B132: KH131 | C132: private | D132: 913805528
A133: bùi văn tuấn | B133: KH132 | C133: private | D133: 986707939
A134: ông nguyễn minh thành | B134: KH133 | C134: private | D134: 972324567
A135: đỗ hoàng nam | B135: KH134 | C135: private | D135: 919096942
A136: trần văn ơn | B136: KH135 | C136: private | D136: 827878938
A137: ông nguyễn văn trường | B137: KH136 | C137: private | D137: 981275787
A138: huỳnh quang phú | B138: KH137 | C138: private | D138: 903579729
A139: ông ninh quang thuận | B139: KH138 | C139: private | D139: 903814168
A140: nguyễn kính tùng | B140: KH139 | C140: private | D140: 944338857
A141: ông nguyễn viết dũng | B141: KH140 | C141: private | D141: 903958931
... A196: nguyễn phạm triệu vũ | B196: KH195 | C196: private | D196: 905125245
A197: công ty tnhh itl vsip | B197: KH196 | C197: company
A198: ông lê hải đăng | B198: KH197 | C198: private | D198: 983106886
A199: huỳnh ngọc quang | B199: KH198 | C199: private | D199: 915422221
A200: lê thị hạnh | B200: KH199 | C200: private | D200: 915155357
...

Sheet shipping inf
A1: region | B1: province_old | C1: province_new | D1: area_type | E1: shipping_cost
A2: Miền Bắc | B2: Hà Nội | C2: Hà Nội | D2: suburban | E2: 30000000
A3: Miền Bắc | B3: Cao Bằng | C3: Cao Bằng | D3: suburban | E3: 30000000
A4: Miền Bắc | B4: Điện Biên | C4: Điện Biên | D4: suburban | E4: 30000000
A5: Miền Bắc | B5: Lai Châu | C5: Lai Châu | D5: suburban | E5: 30000000
A6: Miền Bắc | B6: Sơn La | C6: Sơn La | D6: suburban | E6: 30000000
A7: Miền Bắc | B7: Lạng Sơn | C7: Lạng Sơn | D7: suburban | E7: 30000000
A8: Miền Bắc | B8: Quảng Ninh | C8: Quảng Ninh | D8: suburban | E8: 30000000
A9: Miền Bắc | B9: Thanh Hóa | C9: Thanh Hóa | D9: suburban | E9: 30000000
A10: Miền Bắc | B10: Nghệ An | C10: Nghệ An | D10: suburban | E10: 30000000
A11: Miền Bắc | B11: Hà Giang | C11: Tuyên Quang | D11: suburban | E11: 30000000
A12: Miền Bắc | B12: Tuyên Quang | C12: Tuyên Quang | D12: suburban | E12: 30000000
A13: Miền Bắc | B13: Lào Cai | C13: Lào Cai | D13: suburban | E13: 30000000
... A64: Miền Trung | B64: Phú Yên | C64: Đắk Lắk | D64: suburban | E64: 25000000

Sheet Product inf
A1: product_name | B1: product_ID | C1: product_origin
A2: Belt - Nhật Bản | B2: SP001 | C2: Nhật Bản
A3: Belt - Trung Quốc | B3: SP002 | C3: Trung Quốc
A4: Fuji Korea - Hàn Quốc | B4: SP003 | C4: Hàn Quốc
A5: Motor Mitsubishi - Nhật Bản | B5: SP004 | C5: Nhật Bản
A6: Sanotec - Eco Trung Quốc | B6: SP005 | C6: Trung Quốc
A7: Sanotec - Nhật Bản | B7: SP006 | C7: Nhật Bản
A8: Sanotec - Nidec | B8: SP007 | C8: Thụy Sỹ
A9: Sanotec - Trung Quốc | B9: SP008 | C9: Trung Quốc
A10: Sanotec Eco - Nhật Bản | B10: SP009 | C10: Nhật Bản
A11: Sanotec Eco - Trung Quốc | B11: SP010 | C11: Trung Quốc
A12: Sanotec HP - Trung Quốc | B12: SP011 | C12: Trung Quốc
... A16: Ziehl-Abegg - Đức | B16: SP015 | C16: Đức

Sheet Saleman inf
A1: Saleman_name | B1: posision | C1: saleman_ID
A2: ĐỖ HỒNG VĂN | B2: Dept. 1 | C2: D1001
A3: TRƯƠNG TRỌNG THỊNH | B3: Dept. 1 | C3: D1002
A4: TRẦN ĐỨC THUẬN | B4: Dept. 1 | C4: D1003
A5: DƯƠNG MINH LÊ QUỲNH | B5: Dept. 1 | C5: D1004
A6: UNG TRIỆU THẮNG | B6: Dept. 2 | C6: D2001
A7: NGUYỄN HOÀNG MINH THÁI | B7: Dept. 2 | C7: D2002
A8: NGUYỄN DUY PHƯỚC | B8: Dept. 2 | C8: D2003
A9: PHẠM TẤN ĐỨC | B9: Dept. 2 | C9: D2004
A10: NGUYỄN THẾ ĐỨC DUY | B10: Dept. 2 | C10: D2005
A11: NGUYỄN BẢO HUY | B11: Dept. 2 | C11: D2006
A12: NGUYỄN ANH VŨ | B12: Dept. 2 | C12: D2007
... A22: TRẦN THANH LIÊM | B22: Dept. 4 | C22: D4001

Sheet Saleman_KPI
A1: Saleman_name | B1: saleman_ID | C1: Month | D1: Year | E1: import_staff | F1: KPI_units
A2: ĐỖ HỒNG VĂN | B2: D1001 | C2: 1 | D2: 2024 | E2: D100112024
A3: TRƯƠNG TRỌNG THỊNH | B3: D1002 | C3: 1 | D3: 2024 | E3: D100212024
A4: TRẦN ĐỨC THUẬN | B4: D1003 | C4: 1 | D4: 2024 | E4: D100312024 | F4: 2
A5: DƯƠNG MINH LÊ QUỲNH | B5: D1004 | C5: 1 | D5: 2024 | E5: D100412024
A6: UNG TRIỆU THẮNG | B6: D2001 | C6: 1 | D6: 2024 | E6: D200112024
A7: NGUYỄN HOÀNG MINH THÁI | B7: D2002 | C7: 1 | D7: 2024 | E7: D200212024
A8: NGUYỄN DUY PHƯỚC | B8: D2003 | C8: 1 | D8: 2024 | E8: D200312024
A9: PHẠM TẤN ĐỨC | B9: D2004 | C9: 1 | D9: 2024 | E9: D200412024
A10: NGUYỄN THẾ ĐỨC DUY | B10: D2005 | C10: 1 | D10: 2024 | E10: D200512024 | F10: 1
A11: NGUYỄN BẢO HUY | B11: D2006 | C11: 1 | D11: 2024 | E11: D200612024
A12: NGUYỄN ANH VŨ | B12: D2007 | C12: 1 | D12: 2024 | E12: D200712024
A13: NGUYỄN THANH TÙNG | B13: D2008 | C13: 1 | D13: 2024 | E13: D200812024
A14: NGUYỄN VĂN SƠN | B14: D2009 | C14: 1 | D14: 2024 | E14: D200912024
A15: VÕ KHÁNH DUY | B15: D2010 | C15: 1 | D15: 2024 | E15: D201012024
A16: TRẦN MINH TIẾN | B16: D2011 | C16: 1 | D16: 2024 | E16: D201112024
A17: DƯƠNG QUỐC KIÊN | B17: D2012 | C17: 1 | D17: 2024 | E17: D201212024
A18: TRẦN THẾ TRUNG | B18: D2013 | C18: 1 | D18: 2024 | E18: D201312024 | F18: 1
A19: VÒNG NGUYỄN NGỌC OANH | B19: D3001 | C19: 1 | D19: 2024 | E19: D300112024
A20: TRẦN MINH TIẾN B2B | B20: D3002 | C20: 1 | D20: 2024 | E20: D300212024
A21: LÂM TÂM HÙNG | B21: D3003 | C21: 1 | D21: 2024 | E21: D300312024
A22: TRẦN THANH LIÊM | B22: D4001 | C22: 1 | D22: 2024 | E22: D400112024 | F22: 2
A23: ĐỖ HỒNG VĂN | B23: D1001 | C23: 2 | D23: 2024 | E23: D100122024 | F23: 3
A24: TRƯƠNG TRỌNG THỊNH | B24: D1002 | C24: 2 | D24: 2024 | E24: D100222024
A25: TRẦN ĐỨC THUẬN | B25: D1003 | C25: 2 | D25: 2024 | E25: D100322024 | F25: 3
A26: DƯƠNG MINH LÊ QUỲNH | B26: D1004 | C26: 2 | D26: 2024 | E26: D100422024
A27: UNG TRIỆU THẮNG | B27: D2001 | C27: 2 | D27: 2024 | E27: D200122024
A28: NGUYỄN HOÀNG MINH THÁI | B28: D2002 | C28: 2 | D28: 2024 | E28: D200222024 | F28: 2
A29: NGUYỄN DUY PHƯỚC | B29: D2003 | C29: 2 | D29: 2024 | E29: D200322024
A30: PHẠM TẤN ĐỨC | B30: D2004 | C30: 2 | D30: 2024 | E30: D200422024
A31: NGUYỄN THẾ ĐỨC DUY | B31: D2005 | C31: 2 | D31: 2024 | E31: D200522024 | F31: 1
A32: NGUYỄN BẢO HUY | B32: D2006 | C32: 2 | D32: 2024 | E32: D200622024 | F32: 1
A33: NGUYỄN ANH VŨ | B33: D2007 | C33: 2 | D33: 2024 | E33: D200722024
A34: NGUYỄN THANH TÙNG | B34: D2008 | C34: 2 | D34: 2024 | E34: D200822024
A35: NGUYỄN VĂN SƠN | B35: D2009 | C35: 2 | D35: 2024 | E35: D200922024
A36: VÕ KHÁNH DUY | B36: D2010 | C36: 2 | D36: 2024 | E36: D201022024
A37: TRẦN MINH TIẾN | B37: D2011 | C37: 2 | D37: 2024 | E37: D201122024
A38: DƯƠNG QUỐC KIÊN | B38: D2012 | C38: 2 | D38: 2024 | E38: D201222024
A39: TRẦN THẾ TRUNG | B39: D2013 | C39: 2 | D39: 2024 | E39: D201322024
A40: VÒNG NGUYỄN NGỌC OANH | B40: D3001 | C40: 2 | D40: 2024 | E40: D300122024
A41: TRẦN MINH TIẾN B2B | B41: D3002 | C41: 2 | D41: 2024 | E41: D300222024
A42: LÂM TÂM HÙNG | B42: D3003 | C42: 2 | D42: 2024 | E42: D300322024 | F42: 2
A43: TRẦN THANH LIÊM | B43: D4001 | C43: 2 | D43: 2024 | E43: D400122024 | F43: 1
A44: ĐỖ HỒNG VĂN | B44: D1001 | C44: 3 | D44: 2024 | E44: D100132024 | F44: 1
A45: TRƯƠNG TRỌNG THỊNH | B45: D1002 | C45: 3 | D45: 2024 | E45: D100232024 | F45: 2
A46: TRẦN ĐỨC THUẬN | B46: D1003 | C46: 3 | D46: 2024 | E46: D100332024
A47: DƯƠNG MINH LÊ QUỲNH | B47: D1004 | C47: 3 | D47: 2024 | E47: D100432024
A48: UNG TRIỆU THẮNG | B48: D2001 | C48: 3 | D48: 2024 | E48: D200132024 | F48: 2
A49: NGUYỄN HOÀNG MINH THÁI | B49: D2002 | C49: 3 | D49: 2024 | E49: D200232024
A50: NGUYỄN DUY PHƯỚC | B50: D2003 | C50: 3 | D50: 2024 | E50: D200332024 | F50: 1
A51: PHẠM TẤN ĐỨC | B51: D2004 | C51: 3 | D51: 2024 | E51: D200432024 | F51: 3
A52: NGUYỄN THẾ ĐỨC DUY | B52: D2005 | C52: 3 | D52: 2024 | E52: D200532024 | F52: 3
A53: NGUYỄN BẢO HUY | B53: D2006 | C53: 3 | D53: 2024 | E53: D200632024 | F53: 1
A54: NGUYỄN ANH VŨ | B54: D2007 | C54: 3 | D54: 2024 | E54: D200732024
A55: NGUYỄN THANH TÙNG | B55: D2008 | C55: 3 | D55: 2024 | E55: D200832024
A56: NGUYỄN VĂN SƠN | B56: D2009 | C56: 3 | D56: 2024 | E56: D200932024
A57: VÕ KHÁNH DUY | B57: D2010 | C57: 3 | D57: 2024 | E57: D201032024
A58: TRẦN MINH TIẾN | B58: D2011 | C58: 3 | D58: 2024 | E58: D201132024 | F58: 7
A59: DƯƠNG QUỐC KIÊN | B59: D2012 | C59: 3 | D59: 2024 | E59: D201232024
A60: TRẦN THẾ TRUNG | B60: D2013 | C60: 3 | D60: 2024 | E60: D201332024
A61: VÒNG NGUYỄN NGỌC OANH | B61: D3001 | C61: 3 | D61: 2024 | E61: D300132024 | F61: 1
A62: TRẦN MINH TIẾN B2B | B62: D3002 | C62: 3 | D62: 2024 | E62: D300232024
A63: LÂM TÂM HÙNG | B63: D3003 | C63: 3 | D63: 2024 | E63: D300332024
A64: TRẦN THANH LIÊM | B64: D4001 | C64: 3 | D64: 2024 | E64: D400132024 | F64: 2
A65: ĐỖ HỒNG VĂN | B65: D1001 | C65: 4 | D65: 2024 | E65: D100142024
A66: TRƯƠNG TRỌNG THỊNH | B66: D1002 | C66: 4 | D66: 2024 | E66: D100242024
A67: TRẦN ĐỨC THUẬN | B67: D1003 | C67: 4 | D67: 2024 | E67: D100342024
A68: DƯƠNG MINH LÊ QUỲNH | B68: D1004 | C68: 4 | D68: 2024 | E68: D100442024
A69: UNG TRIỆU THẮNG | B69: D2001 | C69: 4 | D69: 2024 | E69: D200142024
A70: NGUYỄN HOÀNG MINH THÁI | B70: D2002 | C70: 4 | D70: 2024 | E70: D200242024 | F70: 1
A71: NGUYỄN DUY PHƯỚC | B71: D2003 | C71: 4 | D71: 2024 | E71: D200342024 | F71: 4
A72: PHẠM TẤN ĐỨC | B72: D2004 | C72: 4 | D72: 2024 | E72: D200442024 | F72: 4
A73: NGUYỄN THẾ ĐỨC DUY | B73: D2005 | C73: 4 | D73: 2024 | E73: D200542024
A74: NGUYỄN BẢO HUY | B74: D2006 | C74: 4 | D74: 2024 | E74: D200642024
A75: NGUYỄN ANH VŨ | B75: D2007 | C75: 4 | D75: 2024 | E75: D200742024
A76: NGUYỄN THANH TÙNG | B76: D2008 | C76: 4 | D76: 2024 | E76: D200842024
A77: NGUYỄN VĂN SƠN | B77: D2009 | C77: 4 | D77: 2024 | E77: D200942024
A78: VÕ KHÁNH DUY | B78: D2010 | C78: 4 | D78: 2024 | E78: D201042024 | F78: 8
A79: TRẦN MINH TIẾN | B79: D2011 | C79: 4 | D79: 2024 | E79: D201142024
A80: DƯƠNG QUỐC KIÊN | B80: D2012 | C80: 4 | D80: 2024 | E80: D201242024
A81: TRẦN THẾ TRUNG | B81: D2013 | C81: 4 | D81: 2024 | E81: D201342024 | F81: 1
A82: VÒNG NGUYỄN NGỌC OANH | B82: D3001 | C82: 4 | D82: 2024 | E82: D300142024 | F82: 2
A83: TRẦN MINH TIẾN B2B | B83: D3002 | C83: 4 | D83: 2024 | E83: D300242024
A84: LÂM TÂM HÙNG | B84: D3003 | C84: 4 | D84: 2024 | E84: D300342024
A85: TRẦN THANH LIÊM | B85: D4001 | C85: 4 | D85: 2024 | E85: D400142024 | F85: 4
A86: ĐỖ HỒNG VĂN | B86: D1001 | C86: 5 | D86: 2024 | E86: D100152024
A87: TRƯƠNG TRỌNG THỊNH | B87: D1002 | C87: 5 | D87: 2024 | E87: D100252024
A88: TRẦN ĐỨC THUẬN | B88: D1003 | C88: 5 | D88: 2024 | E88: D100352024 | F88: 2
A89: DƯƠNG MINH LÊ QUỲNH | B89: D1004 | C89: 5 | D89: 2024 | E89: D100452024
A90: UNG TRIỆU THẮNG | B90: D2001 | C90: 5 | D90: 2024 | E90: D200152024 | F90: 2
A91: NGUYỄN HOÀNG MINH THÁI | B91: D2002 | C91: 5 | D91: 2024 | E91: D200252024 | F91: 1
A92: NGUYỄN DUY PHƯỚC | B92: D2003 | C92: 5 | D92: 2024 | E92: D200352024 | F92: 1
A93: PHẠM TẤN ĐỨC | B93: D2004 | C93: 5 | D93: 2024 | E93: D200452024
A94: NGUYỄN THẾ ĐỨC DUY | B94: D2005 | C94: 5 | D94: 2024 | E94: D200552024
A95: NGUYỄN BẢO HUY | B95: D2006 | C95: 5 | D95: 2024 | E95: D200652024
A96: NGUYỄN ANH VŨ | B96: D2007 | C96: 5 | D96: 2024 | E96: D200752024
A97: NGUYỄN THANH TÙNG | B97: D2008 | C97: 5 | D97: 2024 | E97: D200852024
A98: NGUYỄN VĂN SƠN | B98: D2009 | C98: 5 | D98: 2024 | E98: D200952024 | F98: 8
A99: VÕ KHÁNH DUY | B99: D2010 | C99: 5 | D99: 2024 | E99: D201052024
A100: TRẦN MINH TIẾN | B100: D2011 | C100: 5 | D100: 2024 | E100: D201152024
...
